{
  "book_name": "60894805-eb5f-40dc-8999-c8c75c032bed_SKN.S303_vn_active",
  "id": "60894805-eb5f-40dc-8999-c8c75c032bed",
  "sku": "SKN.S303",
  "title": "Tư duy phản biện - Cách để không bị thao túng và bị \"lừa\"",
  "market": "vn",
  "language": "vi",
  "has_toc": true,
  "chapters": [
    {
      "index": 1,
      "title": "Chương 1: Hiểu về tư duy phản biện",
      "chapter_stem": "ch001_Chuong_1_Hieu_ve_tu_duy_phan_b",
      "summary": "**1. Luận điểm trung tâm**  \nChương 1 “Hiểu về tư duy phản biện” khẳng định: Tư duy phản biện không phải là sự tranh cãi hay đối đầu, mà là quá trình sử dụng lý trí, phân tích, đánh giá khách quan và xây dựng để tiếp cận vấn đề một cách toàn diện. Tác giả hướng dẫn người đọc nhận diện, phân biệt tư duy phản biện với phản đối và phê bình, cũng như nhấn mạnh vai trò, lợi ích thực tiễn của kỹ năng này trong đời sống, học tập, công việc và xã hội.\n\n---\n\n**2. Khái niệm & framework được giới thiệu**  \n*Khái niệm tư duy phản biện*  \n- Tư duy phản biện là quá trình sử dụng lý trí để phân tích, đánh giá, so sánh và giải thích vấn đề từ nhiều góc độ, nhằm đưa ra cái nhìn toàn diện, khách quan và xây dựng, thay vì chỉ bảo vệ quan điểm cá nhân.\n\n*Framework 4 bước của tư duy phản biện*  \n1. **Phân tích**:  \n   - Chia nhỏ vấn đề để hiểu rõ từng phần.\n   - Xác định vấn đề cốt lõi, liệt kê các thành phần liên quan, tìm mối liên hệ nhân quả.\n2. **Đánh giá**:  \n   - Xem xét độ trung thực, tin cậy, logic của thông tin.\n   - Kiểm tra nguồn gốc, tính nhất quán và sự hữu ích của thông tin.\n3. **So sánh**:  \n   - Đối chiếu cùng một vấn đề ở nhiều nguồn/bối cảnh/góc nhìn khác nhau.\n   - Tìm điểm tương đồng-khác biệt, đối chiếu trên nhiều khía cạnh (thời gian, địa điểm, lĩnh vực…).\n4. **Giải thích**:  \n   - Trình bày kết quả phân tích, đánh giá, so sánh một cách mạch lạc, rõ ràng, có dữ liệu cụ thể, dự đoán phản biện.\n\n*Phân biệt ba khái niệm:*\n- **Phản biện**: Làm rõ, khai mở vấn đề, góp phần cải thiện giải pháp, dùng lập luận, số liệu, và sẵn sàng điều chỉnh quan điểm, tính xây dựng cao.\n- **Phản đối**: Thể hiện sự không đồng tình, thường dựa cảm xúc, ít bằng chứng, dễ gây căng thẳng, ít tính xây dựng.\n- **Phê bình**: Chỉ ra lỗi sai, thúc đẩy cải thiện (nếu xây dựng), nếu không dễ thành chỉ trích, chế giễu.\n\n---\n\n**3. Ví dụ & câu chuyện thực tế**  \n- **Ngụ ngôn “Những người mù sờ voi”**:  \n  Nhóm thầy bói mù mỗi người sờ một bộ phận con voi và mô tả khác nhau. Ai cũng khăng khăng mình đúng, dẫn đến tranh cãi mà không nhận ra mỗi người chỉ biết một phần. Bài học: Nếu thiếu tư duy phản biện, dễ rơi vào cái bẫy chủ quan, không thấy được toàn bộ sự thật.\n\n- **Đánh giá quảng cáo thực phẩm thần kỳ**:  \n  Khi gặp quảng cáo về thực phẩm thần kỳ, người có tư duy phản biện sẽ kiểm tra nguồn, tìm dữ liệu, tránh tin vào những lời lẽ thiếu căn cứ.\n\n- **Mua điện thoại**:  \n  So sánh giá, tính năng, bảo hành ở nhiều nơi trước khi quyết định, thay vì mua vội vàng.\n\n- **Thuyết trình kế hoạch kinh doanh**:  \n  Phân tích bối cảnh, khảo sát, so sánh thị trường, rồi kết luận rõ ràng, mạch lạc.\n\n- **Chống lừa đảo online**:  \n  Nhận tin nhắn trúng thưởng, người có tư duy phản biện sẽ đặt câu hỏi về nguồn, tính xác thực, kiểm chứng thông tin, tránh bị lừa đảo.\n\n- **Chọn ngành học**:  \n  Phân tích sở thích, triển vọng ngành, rủi ro thay vì chỉ nghe theo số đông.\n\n- **Đánh giá ý tưởng quảng cáo tại công ty**:  \n  Phân tích rủi ro, so sánh với các chiến dịch trước, hỏi ý kiến các bộ phận liên quan, thay vì chạy theo số đông.\n\n- **Làm bài thuyết trình tiết kiệm năng lượng**:  \n  Đặt câu hỏi nguyên nhân lãng phí, so sánh mô hình công ty khác, tìm giải pháp sáng tạo (cảm biến tự động, tuyên truyền…).\n\n- **Xử lý phản hồi trái chiều trong họp**:  \n  Lắng nghe, đặt câu hỏi, chuẩn bị bằng chứng để bảo vệ hoặc điều chỉnh quan điểm.\n\n- **Giải quyết mâu thuẫn giữa hai phòng ban**:  \n  Phân tích cả hai góc nhìn (A ưu tiên tốc độ, B chú trọng chất lượng), so sánh kết quả, kết hợp thế mạnh hai bên tìm giải pháp win-win.\n\n- **Văn hóa phản biện ở Israel và phương Tây**:  \n  - Ở Israel, cấp dưới có thể phản biện cấp trên nếu thấy vấn đề, giúp phát triển tinh thần sáng tạo, độc lập.\n  - Ở phương Tây, trẻ em được rèn luyện tư duy phản biện qua tranh luận từ nhỏ, chuyển đổi vai trò ủng hộ/phản đối để rèn khả năng nhìn đa chiều.\n  - Tại Việt Nam, tư duy phản biện còn e dè do truyền thống tôn trọng, nhưng đang dần được khuyến khích ở trường học, doanh nghiệp.\n\n---\n\n**4. Hướng dẫn & bước thực hiện**  \n- Để thực hành tư duy phản biện, tác giả đề xuất:\n  1. **Phân tích**: Khi gặp vấn đề, hãy chia nhỏ, xác định phần cốt lõi, liệt kê các yếu tố liên quan, xác định mối liên hệ nhân – quả.\n  2. **Đánh giá**: Kiểm tra nguồn thông tin, kiểm tra tính nhất quán, xác định giá trị thông tin với mục tiêu của mình.\n  3. **So sánh**: Tìm hiểu vấn đề qua nhiều nguồn, nhiều bối cảnh, so sánh các khía cạnh, nhận diện điểm giống và khác.\n  4. **Giải thích**: Trình bày ý tưởng theo trình tự, minh bạch số liệu, ngắn gọn, sẵn sàng dự đoán phản biện.\n- Khi gặp thông tin hoặc tình huống mới:\n  - Đặt câu hỏi: “Tại sao?”, “Thật sự có bằng chứng không?”, “Có nguồn tin khác xác nhận không?”, “Có góc nhìn nào mình đang bỏ sót?”\n  - Luôn kiểm tra lại cả quan điểm của bản thân, tránh thành kiến.\n  - Lắng nghe ý kiến khác, tìm điểm hợp lý để điều chỉnh hoặc bảo vệ quan điểm dựa trên dữ liệu.\n  - Phối hợp, dung hòa khác biệt để tìm giải pháp chung thay vì tranh cãi vô bổ.\n\n---\n\n**5. Điểm then chốt cần nhớ**  \n1. **Tư duy phản biện là công cụ giúp nhận diện, phân tích, đánh giá và tổng hợp vấn đề một cách khách quan, toàn diện, không nhằm mục đích tranh cãi hay bác bỏ đơn thuần.**\n2. **Có 4 bước cốt lõi trong tư duy phản biện: phân tích, đánh giá, so sánh, giải thích – mỗi bước đều cần sự lý trí, kiểm tra thông tin, đối chiếu đa chiều.**\n3. **Phân biệt rõ phản biện, phản đối và phê bình để tránh nhầm lẫn và sử dụng đúng cách trong giao tiếp, giải quyết vấn đề.**\n4. **Tư duy phản biện giúp bạn tự bảo vệ mình trước thông tin sai lệch, ra quyết định sáng suốt, phát triển tư duy logic – sáng tạo, tự tin và xây dựng trong mọi tình huống.**\n5. **Văn hóa phản biện cần được nuôi dưỡng từ cá nhân đến tập thể, là nền tảng cho sáng tạo, hợp tác, trách nhiệm và tiến bộ xã hội.**"
    },
    {
      "index": 2,
      "title": "Chương 2: Công cụ để nhận diện các bẫy tư duy và đánh giá thiếu chính xác",
      "chapter_stem": "ch002_Chuong_2_Cong_cu_e_nhan_dien_c",
      "summary": "**1. Luận điểm trung tâm**  \nChương 2 tập trung vào việc chỉ ra lý do tại sao con người thường đưa ra những đánh giá thiếu chính xác và dễ rơi vào bẫy tư duy khi tiếp nhận thông tin, đặc biệt trong bối cảnh thời đại số và mạng xã hội. Tác giả nhấn mạnh rằng các lỗ hổng nhận thức này là nguyên nhân khiến nhiều người tin vào tin đồn, mô hình đầu tư siêu lợi nhuận, hoặc những hiện tượng kỳ lạ mà không kiểm chứng kỹ. Để giúp người đọc nhận diện và phòng tránh các bẫy này, chương này giới thiệu Quy tắc 3C (Kiểm tra – So sánh – Đặt vào bối cảnh) như một công cụ thực tiễn giúp xác thực thông tin, nâng cao khả năng tư duy phản biện và giảm thiểu rủi ro mắc sai lầm do nhận thức lệch lạc.\n\n---\n\n**2. Khái niệm & framework được giới thiệu**\n\n**a. Các bẫy tư duy phổ biến**\n- **Hiệu ứng hào quang (Halo Effect):** Đánh giá một người/sự vật dựa trên ấn tượng ban đầu hoặc một dấu hiệu tích cực, dẫn đến thiên vị đánh giá tổng thể.\n- **Bẫy xác nhận thiên kiến (Confirmation Bias):** Chỉ tìm kiếm, ghi nhớ hoặc tin vào thông tin phù hợp với quan điểm cá nhân, bỏ qua dữ liệu phản bác.\n- **Bẫy tin giật gân:** Dễ bị thu hút, tin và chia sẻ những tin tức gây sốc, cảm xúc mạnh mà không kịp kiểm chứng.\n- **FOMO (Fear of Missing Out):** Sợ bỏ lỡ cơ hội, dẫn tới quyết định vội vàng theo số đông hoặc hành động thiếu cân nhắc.\n- **Neo tâm lý (Anchoring):** Bị \"neo\" vào thông tin đầu tiên nhận được, dùng nó làm chuẩn để đánh giá các thông tin tiếp theo.\n- **Bẫy đám đông:** Dễ làm theo hành động, niềm tin của số đông mà thiếu suy xét độc lập.\n\n**b. Quy tắc 3C (Check – Compare – Context)**\n- **Check (Kiểm tra nguồn):** Xác định nguồn thông tin, mức độ tin cậy, có bằng chứng/thẩm định không, nhận diện các yếu tố giả mạo.\n- **Compare (So sánh):** Đối chiếu thông tin với nhiều nguồn độc lập để phát hiện mâu thuẫn, xác nhận chéo, tránh tin vào một chiều.\n- **Context (Đặt vào bối cảnh):** Xem xét tổng thể, hoàn cảnh, mục đích, thời gian phát ngôn/thông tin để hiểu đúng ý nghĩa, tránh bị cắt xén, bóp méo sự thật.\n\n---\n\n**3. Ví dụ & câu chuyện thực tế**\n\n**a. Câu chuyện con gà đẻ trứng vàng**\n- **Nhân vật/tình huống:** Ở một làng nọ, lan truyền tin về con gà đẻ trứng vàng, mỗi ngày cho ra quả trứng sáng lấp lánh, giá trị bằng cả gia tài. Người dân đổ xô đến, tranh nhau mua với giá rất cao.\n- **Diễn biến:** Một thợ kim hoàn kiểm tra kỹ, phát hiện trứng chỉ là trứng thường được sơn màu vàng. Tin vỡ lở, dân làng nhận ra bị lừa.\n- **Bài học:** Câu chuyện này minh họa nhiều bẫy tư duy: hiệu ứng hào quang (trứng vàng lấp lánh gây ấn tượng mạnh), bẫy xác nhận thiên kiến (người dân chỉ tin vào điều mình muốn tin), bẫy tin giật gân (tin đồn lan truyền chóng mặt), FOMO (sợ bỏ lỡ cơ hội giàu sang, ai cũng lao vào mua). Đây là ví dụ điển hình cho việc nhận thức lệch lạc dẫn đến quyết định sai lầm.\n\n**b. Ví dụ áp dụng Quy tắc 3C**\n- **Kiểm tra nguồn (Check):**\n    - Nhận email lạ thông báo trúng thưởng 1 tỷ đồng từ Công ty ABC. Kiểm tra trên Google, không thấy website chính thức, tìm thấy cảnh báo lừa đảo, email gửi đến có tên miền lạ. Kết luận: Lừa đảo, tránh mất thông tin/tiền bạc.\n- **So sánh (Compare):**\n    - Nhận tờ rơi về gói bảo hiểm chi trả 1 tỷ đồng, phí chỉ 99.000 đồng/tháng, không cần khám sức khỏe. So sánh với các công ty bảo hiểm uy tín, thấy mức phí và điều kiện hoàn toàn khác biệt, gọi lên hiệp hội xác nhận công ty không được cấp phép, tra cứu đánh giá người dùng đều cảnh báo lừa đảo. Kết luận: Không mua, tránh bị lừa.\n- **Đặt vào bối cảnh (Context):**\n    - Xem video 15 giây cắt ghép lời giáo viên T nói trường sắp đóng cửa. Kiểm tra bối cảnh, phát hiện đoạn cắt từ buổi họp phụ huynh diễn ra 6 tháng trước, nội dung thực tế là kêu gọi tài trợ nâng cấp cơ sở vật chất, không phải trường sắp đóng. Kết luận: Không hành động vội vàng dựa trên tin đồn.\n\n---\n\n**4. Hướng dẫn & bước thực hiện**\n\n**a. Nhận diện các bẫy tư duy:**\n- Tự hỏi bản thân có đang bị ảnh hưởng bởi hiệu ứng hào quang, xác nhận thiên kiến, FOMO, bẫy đám đông, bẫy tin giật gân, neo tâm lý không.\n- Đặc biệt thận trọng với tin tức quá hấp dẫn, lạ lùng hoặc khiến cảm xúc dâng cao.\n\n**b. Áp dụng Quy tắc 3C:**\n\n**Bước 1: Kiểm tra nguồn (Check)**\n- Xác định nguồn đưa tin: Ai là người/đơn vị phát ngôn? Có chuyên môn, uy tín không?\n- Tra cứu lịch sử, độ tin cậy của nguồn (Google, báo chí, trang chính thống).\n- Kiểm tra kỹ địa chỉ email, website, số liệu trích dẫn.\n- Để ý dấu hiệu giả mạo (giao diện giống trang thật, bình luận ảo).\n\n**Bước 2: So sánh với nhiều nguồn (Compare)**\n- Tìm kiếm ít nhất 2-3 nguồn độc lập để đối chiếu.\n- So sánh số liệu, thời điểm, chi tiết nội dung giữa các nguồn.\n- Tra cứu ý kiến chuyên gia, diễn đàn, báo chí lớn.\n- Đừng chỉ dựa vào một kênh, một bài viết.\n\n**Bước 3: Đặt vào bối cảnh (Context)**\n- Xem xét ai phát ngôn, thời điểm nào, mục đích gì.\n- Tìm phiên bản đầy đủ (video, văn bản) để hiểu toàn bộ ý nghĩa.\n- Quan sát thời điểm đăng tải, động cơ người đưa tin.\n- Để ý dấu hiệu cắt ghép, bóp méo, giật tít gây sốc.\n\n**Lưu ý:**\n- Quy tắc 3C không để hoài nghi mọi thứ, mà nhằm tạo bộ lọc khách quan.\n- Áp dụng linh hoạt, đầu tư thời gian tùy theo mức độ quan trọng của thông tin.\n- Hướng dẫn người thân, bạn bè cùng kiểm chứng thông tin trước khi tin hay chia sẻ.\n\n**c. Bài tập vận dụng cuối chương**\n- Đưa ra 5 tình huống thực tế, yêu cầu chọn phương án đúng (kiểm tra nguồn, so sánh nhiều nguồn, đặt vào bối cảnh) để luyện tập nhận diện bẫy tư duy và áp dụng Quy tắc 3C.\n\n---\n\n**5. Điểm then chốt cần nhớ**\n\n1. **Các bẫy tư duy như hiệu ứng hào quang, xác nhận thiên kiến, tin giật gân, FOMO, neo tâm lý, bẫy đám đông... khiến con người dễ mắc sai lầm trong đánh giá thông tin.**\n2. **Quy tắc 3C (Kiểm tra nguồn, So sánh, Đặt vào bối cảnh) là công cụ thực tế và hiệu quả để xác thực, sàng lọc thông tin và tránh bị thao túng nhận thức.**\n3. **Việc luyện tập 3C giúp bạn chủ động, tỉnh táo, bảo vệ bản thân trước tin giả, lừa đảo, thao túng truyền thông – chuyển từ tiếp nhận bị động sang sàng lọc chủ động.**\n4. **Không nên tin hoặc chia sẻ thông tin chỉ dựa trên cảm xúc, ấn tượng ban đầu hoặc sự đồng thuận của đám đông mà phải kiểm chứng kỹ lưỡng.**\n5. **Thực hành 3C thường xuyên sẽ hình thành kỹ năng phản biện, giúp ra quyết định sáng suốt trong thế giới nhiều loạn thông tin.**"
    },
    {
      "index": 3,
      "title": "Chương 3: Bảo vệ cảm xúc – Đừng để bị dắt mũi",
      "chapter_stem": "ch003_Chuong_3_Bao_ve_cam_xuc_ung_e_",
      "summary": "**1. Luận điểm trung tâm**  \nChương 3 tập trung vào việc giáo dục và thuyết phục người đọc về tầm quan trọng của việc bảo vệ cảm xúc cá nhân khỏi sự thao túng của người khác và các tác nhân bên ngoài (như mạng xã hội, quảng cáo, tin tức giật gân, lừa đảo...). Tác giả nhấn mạnh rằng cảm xúc là một tài sản quý giá nhưng chỉ thực sự có giá trị khi ta biết kiểm soát, không để người khác dẫn dắt, lợi dụng hay “dắt mũi” mình thông qua các chiêu trò kích động cảm xúc. Chương này hướng dẫn cách nhận diện các tình huống dễ bị thao túng, giải thích cơ chế tâm lý – sinh học phía sau sự mất kiểm soát cảm xúc, đồng thời cung cấp các phương pháp và kỹ thuật cụ thể giúp tự bảo vệ và làm chủ cảm xúc, từ đó sống và làm việc tự chủ hơn.\n\n---\n\n**2. Khái niệm & framework được giới thiệu**\n\n- **Kỹ thuật phanh cảm xúc 10 giây:**  \n  Một kỹ thuật giúp ngắt quãng phản ứng cảm xúc bốc đồng bằng cách dừng lại mọi hành động, hít thở sâu, đếm ngược trong 10 giây để chuyển não bộ từ chế độ phản ứng sang chế độ xử lý lý trí.  \n  *Mục tiêu:* Ngăn chặn quyết định bộc phát, giúp tỉnh táo hơn trước khi hành động.\n\n- **Checklist kiểm chứng sự thật 5 bước:**  \n  Một bộ lọc thông tin gồm 5 câu hỏi giúp xác định tính xác thực, động cơ tiềm ẩn của nội dung kích động cảm xúc:\n    1. Nguồn tin là ai?  \n    2. Có bằng chứng, số liệu, chuyên gia không?  \n    3. Đối chiếu thêm với nguồn khác?  \n    4. Nội dung có mục đích đánh vào cảm xúc, bán hàng, câu view?  \n    5. Nếu dừng lại vài phút, bạn có hành động khác không?\n\n- **Bản đồ 3 điểm vượt rừng cảm xúc (A-B-C):**  \n  Một framework mô phỏng hành trình vượt qua sự thao túng cảm xúc:\n    - **A (Bạn đang ở đâu?):** Nhận diện cảm xúc hiện tại, xác định nguồn gốc cảm xúc.\n    - **B (Đối tượng thao túng):** Kiểm tra ngữ cảnh, nguồn gốc, động cơ, cảm xúc bị lợi dụng.\n    - **C (Hướng giải quyết):** Dùng kỹ thuật phanh cảm xúc, kiểm chứng, hỏi ý kiến chuyên gia, hành động lý trí.\n\n---\n\n**3. Ví dụ & câu chuyện thực tế**\n\n- **Câu chuyện của Nam:**  \n  Nam là một người nóng tính, thường xuyên vào mạng xã hội để giải trí nhưng lại dễ bị lôi kéo vào các bài đăng có tiêu đề kích động như “Sốc”, “Kinh hoàng”, “Nhìn mà xem!”. Khi thấy bài chế giễu đội bóng mình yêu thích, Nam nổi giận, lao vào tranh cãi, dùng những lời lẽ gay gắt bảo vệ quan điểm. Hệ quả: Anh mất thời gian, bực bội, ảnh hưởng tới công việc và tinh thần. Sau này anh nhận ra mình bị “dắt mũi” bởi cảm xúc nhất thời từ tiêu đề, hình ảnh, lời lẽ kích động, dẫn đến mất kiểm soát.\n\n- **Ví dụ về lừa đảo qua điện thoại:**  \n  Nhiều người nhận được cuộc gọi giả danh công an, dọa dẫm liên quan đến rửa tiền, yêu cầu nộp phạt nếu không sẽ bị bắt. Vì quá sợ hãi, nhiều nạn nhân làm theo hướng dẫn lừa đảo, mất tiền. Tương tự, phụ huynh nhận cuộc gọi giả danh con gặp nạn, vội vàng chuyển tiền vì hoảng loạn, chỉ khi bình tĩnh lại mới biết bị lừa.\n\n- **Ví dụ về lòng tham – đa cấp, quảng cáo:**  \n  Các mô hình đa cấp, quảng cáo lợi dụng lòng tham, đưa ra viễn cảnh làm giàu nhanh, thu nhập thụ động lớn. Người nghe bị cuốn hút bởi cam kết “kiếm ngay 10 triệu mỗi tuần chỉ với 1 triệu vốn”, không kiểm chứng nguồn tiền, hợp lý hay không. Kết quả: Đầu tư mù quáng, trắng tay.\n\n- **Ví dụ về cảm giác tội lỗi, bị ép buộc:**  \n  Một người thân mở cửa hàng quần áo, ép bạn mua với lý do “là người nhà mà không ủng hộ thì sao?”. Dù không thích sản phẩm, vì sợ bị đánh giá là vô tâm, bạn ngại từ chối và miễn cưỡng mua, để rồi không thoải mái.\n\n- **Ví dụ về kiểm chứng thông tin cảnh báo sức khỏe:**  \n  Bạn nhận tin nhắn “Cảnh báo khẩn, không uống nước sau 10h tối kẻo nguy cơ đột quỵ”, không nguồn, không dẫn chứng. Nếu vội vàng tin và chia sẻ, bạn có thể phát tán tin sai. Nếu dừng lại kiểm chứng (tìm nguồn, hỏi chuyên gia, so sánh báo uy tín), bạn sẽ thấy thông tin này vô căn cứ.\n\n- **Ví dụ về giữ khoảng cách với nguồn gây kích động:**  \n  Nếu một trang mạng hoặc người nào đó liên tục đăng tin tiêu cực (gây lo lắng, tức giận), nên tạm thời ngừng theo dõi để tránh bị ảnh hưởng cảm xúc. Khi ai đó gây áp lực, có thể đáp “Tôi sẽ suy nghĩ thêm, trả lời sau” để tránh bị cuốn theo.\n\n- **Ví dụ về tìm góc nhìn khác:**  \n  Khi định mua sản phẩm được quảng cáo “có cánh”, hãy đọc cả bình luận phê bình, hỏi ý kiến người khác để có đánh giá khách quan, tránh bị cảm xúc nhất thời lấn át lý trí.\n\n---\n\n**4. Hướng dẫn & bước thực hiện**\n\n- **Bước 1: Nhận diện cảm xúc**  \n  - Dừng lại, tự hỏi: Mình đang cảm thấy gì (giận, sợ, tò mò, tội lỗi, hưng phấn…)?  \n  - Cảm xúc này đến từ nội dung vừa tiếp xúc hay có sẵn từ trước?\n\n- **Bước 2: Xác định đối tượng thao túng**  \n  - Kiểm tra ngôn từ, hình ảnh có giật gân, phóng đại, đe dọa, mồi chài không?  \n  - Nguồn gốc, tác giả, động cơ tiềm ẩn (bán hàng, câu view, lừa đảo…)?  \n  - Nội dung đang đánh vào cảm xúc nào của mình?\n\n- **Bước 3: Kỹ thuật phanh cảm xúc 10 giây**  \n  - Ngừng mọi hành động (không phản ứng, không nhắn tin, không tranh cãi).  \n  - Hít thở sâu, đếm ngược 10-0.  \n  - Đánh giá lại cảm xúc: Còn bốc đồng như ban đầu không?\n\n- **Bước 4: Kiểm chứng thông tin**  \n  - Áp dụng checklist 5 câu hỏi (xem phần khái niệm & framework).  \n  - Đối chiếu với nguồn tin khác, hỏi ý kiến chuyên gia hoặc người có kinh nghiệm.\n\n- **Bước 5: Tìm góc nhìn khác**  \n  - Trao đổi với người thân, bạn bè, chuyên gia để lấy ý kiến khách quan.  \n  - Đọc cả ý kiến trái chiều, đa chiều về vấn đề.\n\n- **Bước 6: Giữ khoảng cách với nguồn kích động**  \n  - Chủ động giảm tiếp xúc với những người, trang mạng, nội dung thường xuyên gây cảm xúc tiêu cực.  \n  - Cho bản thân “giải độc thông tin” định kỳ.\n\n- **Bước 7: Thực hành trò chơi vượt rừng cảm xúc (A-B-C):**  \n  - A: Xác định cảm xúc hiện tại.  \n  - B: Nhận diện nguồn, động cơ thao túng.  \n  - C: Ngắt phản ứng, kiểm chứng, hành động lý trí.\n\n---\n\n**5. Điểm then chốt cần nhớ**\n\n1. **Cảm xúc là tài sản quý, nhưng nếu không kiểm soát sẽ dễ bị người khác lợi dụng, thao túng.**\n2. **Não bộ có xu hướng ưu tiên cảm xúc hơn lý trí, khiến chúng ta dễ phản ứng bốc đồng — đặc biệt khi bị kích động giận dữ, sợ hãi, tham lam, tội lỗi…**\n3. **Các chiêu trò thao túng cảm xúc rất đa dạng: tin giật gân, lừa đảo, quảng cáo, ép buộc bằng cảm giác tội lỗi, v.v…**\n4. **Kỹ thuật “phanh cảm xúc 10 giây”, kiểm chứng thông tin, tìm góc nhìn khác và chủ động giữ khoảng cách với nguồn kích động là những công cụ thực tiễn, cực kỳ hiệu quả để làm chủ cảm xúc.**\n5. **Việc rèn luyện kiểm soát cảm xúc là kỹ năng thiết yếu giúp bạn giữ vững sự tự chủ, tránh bị “dắt mũi” và thành công bền vững trong cuộc sống.**"
    },
    {
      "index": 4,
      "title": "Chương 4: Phòng vệ trước tin giả và lừa đảo",
      "chapter_stem": "ch004_Chuong_4_Phong_ve_truoc_tin_gi",
      "summary": "**1. Luận điểm trung tâm**  \nChương này nhấn mạnh rằng mỗi người cần chủ động trang bị cho mình bộ lọc và tư duy phản biện để không trở thành nạn nhân hay vô tình lan truyền tin giả, lừa đảo trong thời đại số. Tác giả chứng minh mức độ nguy hiểm của tin giả/lừa đảo, hướng dẫn cách nhận diện, kiểm chứng thông tin và rèn luyện thói quen cảnh giác cùng kỹ năng số để phòng vệ hiệu quả trước những thủ đoạn ngày càng tinh vi.\n\n---\n\n**2. Khái niệm & framework được giới thiệu**\n\n- **Tin giả (Fake News):** Là thông tin không đúng sự thật (bịa đặt hoàn toàn hoặc sai lệch một phần) được nguy trang thành tin thật và lan truyền rộng rãi, thường nhằm mục đích thao túng dư luận, gây hoang mang hoặc trục lợi.\n- **Lừa đảo trực tuyến:** Hành vi giả mạo, dụ dỗ nhằm chiếm đoạt tài sản, thông tin cá nhân trên internet qua nhiều hình thức như email, tin nhắn, chiêu trò tặng quà, bẫy tình cảm, gây áp lực thời gian, deepfake v.v.\n- **Suy nghĩ chậm:** Thuật ngữ chỉ quá trình suy nghĩ có chủ đích, logic, phân tích thay vì phản ứng tức thời, cảm tính – giúp đánh giá thông tin kỹ lưỡng trước khi tin tưởng hay hành động.\n- **Kỹ thuật “Tạm dừng 10 giây”:** Khi gặp thông tin gây sốc/cảm xúc mạnh, chủ động đếm chậm 10 giây, hít thở sâu để não bộ chuyển sang chế độ lý trí, giúp kiểm tra và suy xét lại trước khi phản ứng.\n- **Phương pháp kiểm chứng thông tin:** Sử dụng các bước kiểm tra nguồn, đối chiếu nhiều nguồn tin, dùng công cụ fact-check, kiểm tra hình ảnh/video, hỏi ý kiến chuyên gia để xác thực tính đúng sai của thông tin.\n\n---\n\n**3. Ví dụ & câu chuyện thực tế**\n\n- **Câu chuyện “Cậu bé chăn cừu”:**  \n  Cậu bé vì nghịch ngợm đã nhiều lần giả vờ kêu gọi dân làng cứu cừu khỏi sói. Lần đầu và lần hai, dân làng chạy đến giúp nhưng phát hiện bị lừa. Đến lần thứ ba, khi sói thật xuất hiện, không ai tin cậu khiến đàn cừu bị ăn thịt.  \n  *Bài học:* Khi tin giả, tin đồn thất thiệt lặp đi lặp lại, cộng đồng mất khả năng phân biệt đúng sai, dẫn đến hậu quả thật.\n\n- **Đầu dịch COVID-19:**  \n  Nhiều tin đồn như “uống nước gừng phòng virus” hay “tỏi chữa COVID-19” lan truyền chóng mặt, khiến người dân đổ xô mua tỏi/gừng, đội giá, gây hoang mang xã hội. Ngoài ra, tin đồn bắt cóc trẻ em lan trên Facebook từng khiến đám đông hành hung nhầm người vô tội.\n\n- **Doanh nghiệp thực phẩm bị vu oan:**  \n  Một công ty bị lan truyền tin “dùng hóa chất độc hại” khiến doanh số sụt giảm, công nhân thất nghiệp. Sau kiểm tra của cơ quan chức năng, phát hiện tin đồn không đúng, nhưng danh tiếng công ty bị ảnh hưởng nặng.\n\n- **Tin giả về vắc-xin:**  \n  Thuyết âm mưu “vắc-xin gây hại nhiều hơn lợi” khiến nhiều người từ chối tiêm chủng, làm dịch bệnh khó kiểm soát, ảnh hưởng đến an toàn cộng đồng.\n\n- **Email ngân hàng lừa đảo:**  \n  Người dùng nhận được email tự xưng ngân hàng, yêu cầu nhấn vào link xác minh tài khoản trong 24h, nếu không sẽ bị khóa. Link này thực chất là giả mạo, nhằm đánh cắp thông tin đăng nhập. Người cảnh giác sẽ không bấm link mà kiểm tra lại qua tổng đài chính thức.\n\n- **Bẫy lừa “trúng thưởng”:**  \n  Thông báo trúng thưởng lớn hoặc “ở nhà kiếm 50 triệu/tháng không cần vốn” nhưng yêu cầu chuyển phí trước – kết quả không ai nhận được quà, chỉ bị lừa tiền hoặc mất thông tin cá nhân.\n\n- **Deepfake lừa tiền qua video call:**  \n  Kẻ xấu dùng công nghệ AI ghép mặt người thân vào cuộc gọi video để lừa đảo. Nếu đã biết phương thức này qua tin tức, người dùng sẽ cảnh giác khi gặp tình huống tương tự.\n\n---\n\n**4. Hướng dẫn & bước thực hiện**\n\n**A. Nhận diện tin giả:**\n- Đặt nghi vấn với các tiêu đề giật gân, gây sốc, in hoa, nhiều dấu chấm than.\n- Kiểm tra nguồn tin: Có trích dẫn uy tín không? Trang web/tác giả có minh bạch, xác thực không?\n- Tìm chi tiết cụ thể: Xem có số liệu, nghiên cứu, chuyên gia nào được dẫn chứng không.\n- Quan sát lỗi chính tả, câu cú bất thường.\n- Đánh giá nội dung: Nếu bài viết mang tính cảm xúc mạnh, một chiều, thiếu logic, dễ là tin giả.\n- Kiểm tra hình ảnh/video: Dùng công cụ tìm kiếm hình ảnh ngược (Google Images, TinEye), chú ý deepfake.\n- Cẩn trọng với những lời kêu gọi chia sẻ gấp, cảnh báo khẩn cấp, thúc giục lan truyền.\n\n**B. Nhận diện lừa đảo trực tuyến:**\n- Cảnh giác email/tin nhắn giả mạo ngân hàng, cơ quan chức năng, người thân xin mật khẩu/OTP, yêu cầu chuyển tiền gấp.\n- Đề phòng chiêu trò “trúng thưởng”, “quà tặng hấp dẫn” nhưng phải chuyển phí trước.\n- Cẩn trọng với bẫy tình cảm (làm quen, yêu đương rồi mượn tiền).\n- Nhận diện áp lực thời gian, dọa dẫm, thúc ép hành động nhanh.\n\n**C. Kiểm chứng thông tin:**\n1. **Xác thực nguồn tin:**\n   - Kiểm tra độ uy tín của trang/tác giả.\n   - Đối chiếu thông tin trên các báo lớn, website chính thống.\n   - Kiểm tra thời gian đăng tin để tránh tin cũ bị đào lại.\n   - Đọc kỹ xem trang đó là trang tin thật hay trang trào phúng/chế.\n\n2. **Sử dụng công cụ fact-check:**\n   - Tìm kiếm thông tin trên Google, thêm từ khóa “tin giả”, “lừa đảo”, “chính xác”, “đính chính”.\n   - Tra cứu các trang xác thực nổi tiếng: Snopes, PolitiFact, FactCheck.org, Tingia.gov.vn.\n   - Đối chiếu nhiều nguồn báo uy tín, lâu năm.\n\n3. **Kiểm tra hình ảnh/video:**\n   - Dùng Google hình ảnh, TinEye để tra ảnh gốc, bối cảnh thật.\n   - Cảnh giác với video cắt ghép, deepfake.\n\n4. **Hỏi ý kiến chuyên gia:**\n   - Với thông tin chuyên môn, tham khảo bác sĩ, luật sư, chuyên viên IT,…\n\n**D. Rèn luyện thói quen cảnh giác:**\n- Áp dụng “suy nghĩ chậm”: Luôn dừng lại vài giây, đặt câu hỏi, đọc kỹ, so sánh, đối chiếu trước khi tin hoặc chia sẻ.\n- Thực hành kỹ thuật “Tạm dừng 10 giây”: Khi xúc động mạnh với thông tin, hãy hít sâu, đếm 1-10, suy nghĩ rồi mới phản ứng.\n- Chủ động tự giáo dục, cập nhật kiến thức về các chiêu trò mới, kỹ năng số (kiểm tra link, bảo mật tài khoản, dùng Google hiệu quả…).\n- Chia sẻ, thảo luận với người thân, bạn bè khi gặp thông tin nghi vấn; lan tỏa văn hóa kiểm chứng.\n- Rèn luyện tư duy phản biện trong đời sống: luôn đặt câu hỏi, phân tích mọi thông tin, quảng cáo, câu chuyện nhận được.\n\n---\n\n**5. Điểm then chốt cần nhớ**\n\n1. **Tin giả và lừa đảo là hiểm họa thực sự, không chừa bất cứ ai – chủ động cảnh giác là lá chắn hiệu quả nhất.**\n2. **Nhận diện dấu hiệu tin giả/lừa đảo: tiêu đề giật gân, thiếu nguồn uy tín, nội dung cảm tính, kêu gọi chia sẻ gấp, hình ảnh/video mập mờ.**\n3. **Áp dụng các bước kiểm chứng thông tin: xác thực nguồn, đối chiếu nhiều nguồn, dùng công cụ fact-check, kiểm tra hình ảnh/video, hỏi chuyên gia.**\n4. **Luôn thực hành “suy nghĩ chậm” và kỹ thuật “Tạm dừng 10 giây” khi gặp thông tin gây cảm xúc mạnh để tránh quyết định hấp tấp.**\n5. **Tự giáo dục, nâng cao kỹ năng số, chia sẻ kiến thức cho người thân và chủ động lan tỏa văn hóa kiểm chứng là cách phòng vệ bền vững nhất trước tin giả, lừa đảo.**"
    },
    {
      "index": 5,
      "title": "Chương 5: Tại sao nhà tuyển dụng săn đón người biết phản biện?",
      "chapter_stem": "ch005_Chuong_5_Tai_sao_nha_tuyen_dun",
      "summary": "**1. Luận điểm trung tâm**  \nChương này lập luận rằng trong bối cảnh tuyển dụng hiện đại, tư duy phản biện là một kỹ năng mềm nổi bật và được các nhà tuyển dụng đặc biệt săn đón. Không chỉ dừng lại ở việc giúp tổ chức giải quyết vấn đề hiệu quả hơn, tư duy phản biện còn trở thành yếu tố tạo nên giá trị cạnh tranh, thúc đẩy đổi mới, tối ưu hóa quy trình và xây dựng văn hóa doanh nghiệp bền vững. Tác giả thuyết phục rằng ứng viên sở hữu tư duy phản biện không chỉ hoàn thành nhiệm vụ mà còn chủ động tạo ra cải tiến, đóng góp dài hạn cho tổ chức, trở thành nguồn lực không thể thiếu trong bất kỳ môi trường làm việc nào.\n\n---\n\n**2. Khái niệm & framework được giới thiệu**\n\n- **Tư duy phản biện (Critical Thinking):**  \n  Là năng lực đặt câu hỏi đúng, phân tích đa chiều, chất lọc dữ liệu và đưa ra giải pháp xây dựng dựa trên lập luận logic và căn cứ thực tiễn. Tư duy này khác với việc phản đối đơn thuần, bởi nó hướng đến mục tiêu giải quyết vấn đề, đổi mới và cải tiến thay vì chỉ bác bỏ ý kiến.\n\n- **Phân biệt Nhân viên phản biện và Nhân viên phản đối:**  \n  - *Nhân viên phản biện* tìm kiếm giải pháp, xây dựng ý tưởng khả thi, dựa trên dữ liệu, lắng nghe và điều chỉnh, đóng góp ý kiến mang tính xây dựng, thúc đẩy cải tiến.\n  - *Nhân viên phản đối* thường chủ quan, thiếu bằng chứng, chỉ trích hoặc chống đối mà không đưa ra phương án giải quyết, dễ gây xung đột cá nhân và trì trệ.\n\n- **Bộ ba năng lực phản biện:**  \n  - Đặt câu hỏi – Giải quyết vấn đề – Xây dựng (Questioning – Problem Solving – Constructing): Đây là ba bước then chốt trong tư duy phản biện, đòi hỏi chủ động, lắng nghe, tổng hợp thông tin trước khi kết luận.\n\n- **Vùng xám thông tin:**  \n  Những khoảng trống, lập lờ trong quy trình, trách nhiệm, dữ liệu… cần được làm rõ bằng tư duy phản biện nhằm tránh sai sót và tối ưu hóa vận hành.\n\n- **Hiệu ứng đuôi cá:**  \n  Hiện tượng các thành viên làm việc rời rạc, ỷ lại, không chủ động. Tư duy phản biện giúp mỗi người tự đánh giá vai trò, đóng góp và tránh tình trạng này.\n\n---\n\n**3. Ví dụ & câu chuyện thực tế**\n\n- **Google:**  \n  Văn hóa khuyến khích đặt câu hỏi “Tại sao?” và nghi ngờ hiện trạng đã giúp Google liên tục tạo ra sản phẩm đột phá như Gmail, Google Maps. Nhân viên được khuyến khích phản biện, góp ý để thúc đẩy đổi mới.\n\n- **Startup Việt Nam:**  \n  Các doanh nghiệp startup thành công thường có đội ngũ trẻ biết đặt vấn đề, thử nghiệm và điều chỉnh nhanh chóng thay vì đi theo lối mòn, nhờ đó tối ưu hóa sản phẩm và dịch vụ.\n\n- **Câu chuyện phỏng vấn tuyển dụng Chuyên viên Phát triển Sản phẩm:**  \n  - *Ứng viên A*: Chỉ biết làm theo chỉ đạo, thiếu tính phản biện, dễ bị động trước rủi ro.\n  - *Ứng viên B*: Chỉ phản đối về thời gian nhưng không đề xuất giải pháp, không có dữ liệu hỗ trợ.\n  - *Ứng viên C*: Đặt câu hỏi làm rõ mục tiêu, phân tích ràng buộc, đề xuất giải pháp MVP, thử nghiệm nội bộ, kế hoạch truyền thông linh hoạt – thể hiện tư duy phản biện vượt trội, được đánh giá cao nhất.\n  - *Bài học*: Tư duy phản biện giúp ứng viên nổi bật, không chỉ hoàn thành việc mà còn chủ động cải tiến.\n\n- **Chuỗi bán lẻ đồ gia dụng online:**  \n  Khi tỷ lệ khách hủy đơn tăng, nhân viên phản biện tìm gốc rễ (phí ship cao, thời gian giao hàng), phân tích nguyên nhân sâu xa (chính sách vận chuyển, đối tác chưa tối ưu) và đề xuất điều chỉnh giúp giảm tỷ lệ hủy đơn.\n\n- **Chuỗi cà phê:**  \n  Doanh số tăng chậm, nhân viên phản biện đề xuất thử nghiệm thêm dòng sản phẩm mới dựa trên khảo sát thị trường. Kết quả là doanh số tăng nhanh nhờ đón nhận tích cực từ khách hàng trẻ.\n\n- **Xưởng may mặc:**  \n  Nhân viên phân tích dữ liệu thị trường, dự báo giá nguyên vật liệu tăng, chủ động đề xuất mua dự trữ/kiếm nhà cung cấp mới, giúp công ty ổn định chi phí khi biến động thị trường xảy ra.\n\n- **Công ty bán lẻ điện tử:**  \n  Khi thấy đối thủ ứng dụng chatbot, nhân viên phản biện phân tích lợi ích và rủi ro, đề xuất áp dụng sớm, giúp tăng doanh số online 15% trước khi đối thủ kịp thích nghi.\n\n- **Công ty sản xuất thép:**  \n  Ban lãnh đạo khuyến khích phản biện đa chiều trong họp giao ban, các phòng ban cùng nhau phân tích rủi ro, nhu cầu vốn, năng lực sản xuất… giúp đề án tăng sản lượng hiệu quả, phòng tránh sai lầm.\n\n- **Doanh nghiệp xây dựng:**  \n  Nhân viên phản biện làm rõ vùng xám về chi phí phát sinh giữa phòng Dự án và Kế toán, thiết lập lại quy trình báo cáo, giảm hiểu lầm và kiểm soát ngân sách tốt hơn.\n\n- **Nhà hàng:**  \n  Khi phục vụ chậm trễ, nhân viên phản biện đề xuất xem lại quy trình thực tế (camera), phát hiện tắc nghẽn ở khu vực chuyển món, giúp quản lý cải tiến không gian làm việc, tăng sự tin cậy giữa các bộ phận.\n\n- **Startup phát triển ứng dụng di động:**  \n  Nhóm sử dụng tư duy phản biện để phân tích điểm mạnh riêng của từng thành viên (phân tích dữ liệu, sáng tạo, giao tiếp khách hàng…), từ đó giao việc đúng người, tăng hiệu quả dự án và tinh thần đồng đội.\n\n- **Công ty startup thương mại điện tử:**  \n  Chiến dịch marketing bị trễ do không ai chủ động. Nhân viên phản biện đặt câu hỏi về trách nhiệm và quy trình, nhóm tự cam kết deadline, báo cáo rõ ràng, cải thiện tiến độ.\n\n- **Agency quảng cáo:**  \n  Nhận ra quá nhiều cuộc họp không cần thiết, nhân viên phản biện đề xuất rút gọn, kết hợp báo cáo online, giúp tiết kiệm thời gian, tăng hiệu quả làm việc.\n\n- **Tổ chức workshop nội bộ:**  \n  Thay vì áp đặt, nhóm cùng phản biện về nội dung, người huấn luyện, thời lượng…, giúp workshop sát thực tế, mọi người hào hứng tham gia.\n\n---\n\n**4. Hướng dẫn & bước thực hiện**\n\n- **Phát triển tư duy phản biện cá nhân:**\n  1. Luôn đặt câu hỏi để làm rõ thông tin, mục tiêu, ràng buộc khi nhận nhiệm vụ.\n  2. Phân tích dữ liệu, đối chiếu nhiều nguồn, nhìn nhận vấn đề đa chiều trước khi kết luận.\n  3. Khi phát hiện vấn đề, không chỉ phản đối mà cần đề xuất ít nhất một giải pháp khả thi, có tính xây dựng.\n  4. Tích cực lắng nghe ý kiến phản hồi, tôn trọng sự khác biệt, học hỏi từ đồng đội.\n  5. Chủ động dự đoán rủi ro, xây dựng các kịch bản “nếu... thì sao?” để đề phòng và kiểm soát biến động.\n  6. Thường xuyên tự đánh giá hiệu quả công việc, không ngại thử nghiệm đổi mới và rút kinh nghiệm.\n\n- **Tạo môi trường phản biện tại doanh nghiệp:**\n  1. Khuyến khích mọi người trình bày quan điểm, đặt câu hỏi, đóng góp ý tưởng.\n  2. Tôn trọng và lắng nghe phản biện, không quy chụp, không chỉ trích cá nhân.\n  3. Xây dựng quy trình làm rõ trách nhiệm, loại bỏ vùng xám thông tin.\n  4. Định kỳ tổ chức thảo luận, hội họp đa chiều, tạo diễn đàn ý kiến đóng góp từ nhiều phòng ban.\n  5. Đánh giá nhân sự không chỉ dựa vào chuyên môn mà còn dựa vào năng lực phân tích, đề xuất cải tiến, khả năng phối hợp nhóm.\n\n---\n\n**5. Điểm then chốt cần nhớ**\n\n1. **Tư duy phản biện là “điểm cộng vô hình” giúp ứng viên nổi bật, được nhà tuyển dụng săn đón trong thời đại mới.**\n2. **Phản biện không phải là phản đối: Bản chất là đặt câu hỏi, phân tích dữ liệu và đưa ra giải pháp xây dựng, dựa trên mục tiêu cải tiến.**\n3. **Nhân sự có tư duy phản biện giúp doanh nghiệp giải quyết gốc rễ vấn đề, đổi mới sáng tạo, kiểm soát rủi ro và tối ưu vận hành.**\n4. **Khuyến khích phản biện tạo ra môi trường làm việc đa chiều, minh bạch, tăng sự gắn kết và phát huy tối đa thế mạnh từng cá nhân.**\n5. **Muốn trở thành ứng viên sáng giá, hãy rèn luyện tư duy phản biện từ hôm nay bằng việc chủ động đặt câu hỏi, phân tích, đề xuất giải pháp và phối hợp xây dựng trong mọi nhiệm vụ.**"
    },
    {
      "index": 6,
      "title": "Chương 6: Kỹ năng phản biện tích cực trong môi trường làm việc",
      "chapter_stem": "ch006_Chuong_6_Ky_nang_phan_bien_tic",
      "summary": "**1. Luận điểm trung tâm**  \nChương 6 lập luận rằng để phát triển và thành công trong môi trường làm việc hiện đại, mỗi cá nhân cần phải rèn luyện kỹ năng phản biện tích cực. Không chỉ dừng lại ở tư duy phản biện, chương này tập trung hướng dẫn cách thực hành phản biện thông minh và xây dựng, giúp giao tiếp hiệu quả với đồng nghiệp, cấp trên, khách hàng mà vẫn đảm bảo sự tôn trọng, hợp tác và hướng đến kết quả chung. Hai yếu tố cốt lõi được nhấn mạnh là: Nghệ thuật đặt câu hỏi thông minh và công thức phản biện tích cực “Khen – Góp ý – Đề xuất”.\n\n---\n\n**2. Khái niệm & framework được giới thiệu**\n\n- **Nghệ thuật đặt câu hỏi thông minh:**  \n  Là kỹ năng sử dụng các dạng câu hỏi phù hợp để làm rõ thông tin, xác định mục tiêu, kiểm chứng dữ liệu, mở rộng góc nhìn, và khơi gợi giải pháp mới. Đặt câu hỏi đúng là “công tắc” của quá trình phản biện, giúp tránh sai lầm, tiết kiệm thời gian, và thể hiện sự tôn trọng người đối diện.\n\n- **Các loại câu hỏi quan trọng**  \n  1. **Câu hỏi làm rõ thông tin:** Xác thực, bổ sung dữ liệu, tránh hiểu nhầm.\n  2. **Câu hỏi mục tiêu:** Tìm hiểu kỳ vọng, mục tiêu dài hạn.\n  3. **Câu hỏi ngược về tính phù hợp:** Kiểm tra tính khả thi, phù hợp với nguồn lực.\n  4. **Câu hỏi mở khơi gợi:** Khơi mở ý tưởng, góc nhìn mới.\n  5. **Câu hỏi so sánh:** So sánh lựa chọn, đánh giá ưu nhược điểm.\n  6. **Câu hỏi kiểm chứng hoặc đối chiếu:** Xác nhận tính chính xác, cập nhật của dữ liệu.\n\n- **Công thức phản biện tích cực Khen – Góp ý – Đề xuất (K-G-Đ):**  \n  Một phương pháp phản biện xây dựng gồm ba bước:\n  1. **Khen (ghi nhận điểm tốt):** Ghi nhận nỗ lực, điểm sáng của ý tưởng/người trình bày.\n  2. **Góp ý (nêu hạn chế, rủi ro):** Đưa ra nhận xét khách quan, cụ thể về điểm cần hoàn thiện.\n  3. **Đề xuất (giải pháp):** Đưa ra hướng giải quyết hoặc ý tưởng thay thế mang tính xây dựng.\n\n---\n\n**3. Ví dụ & câu chuyện thực tế**\n\n- **Tình huống thực tế về hậu quả của không đặt câu hỏi:**\n  - **Nhận dự án với yêu cầu mơ hồ:**  \n    Nhân viên được giao dự án có deadline gắt mà không được làm rõ kỳ vọng hoặc ngân sách. Vì ngại hỏi, bạn vội nhận việc. Đến khi sắp hoàn thành, sếp phản hồi ngân sách chỉ là 50 triệu đồng, khiến toàn bộ kế hoạch phải làm lại. Bài học: Chủ động hỏi sẽ giúp tránh lãng phí công sức, nguồn lực.\n  - **Đồng nghiệp trình bày ý tưởng nhiều tham vọng nhưng thiếu khả thi:**  \n    Do không hỏi kỹ về khả năng thực thi, cả đội sau này phải mất nhiều tuần chỉnh sửa vì thiếu nhân sự. Bài học: Đặt câu hỏi giúp lường trước rủi ro, hoàn thiện giải pháp.\n  - **Khách hàng muốn chiến dịch quảng cáo “lớn”, thực tế ngân sách hạn chế:**  \n    Không hỏi rõ, bạn lên kế hoạch vượt ngân sách, cuối cùng phải sửa lại trong stress. Bài học: Làm rõ nhu cầu, nguồn lực ngay từ đầu là tối quan trọng.\n\n- **Ví dụ đặt câu hỏi thông minh trong họp Kick-off dự án Marketing:**\n  - Đặt câu hỏi về ưu tiên mục tiêu (nhận diện thương hiệu hay doanh số), chỉ tiêu cụ thể, so sánh kênh quảng bá, kiểm chứng dữ liệu khách hàng, và đề xuất giải pháp mở rộng (như hợp tác KOL). Kết quả: Cả đội hiểu rõ mục tiêu, tránh nhầm lẫn, có phương án bổ sung kịp thời.\n\n- **Hai kịch bản phản biện trái ngược:**\n  - **Kịch bản 1: Phản đối gay gắt**  \n    Phản ứng kiểu \"Kế hoạch gì mà phi thực tế thế?\" dẫn đến tranh cãi, mất hòa khí, không giải quyết được vấn đề.\n  - **Kịch bản 2: Phản biện tích cực với K-G-Đ**  \n    Bắt đầu bằng lời khen, nêu góp ý cụ thể, và đề xuất giải pháp thử nghiệm nhỏ trước. Kết quả: Đồng nghiệp hợp tác, không khí xây dựng, ý tưởng được hoàn thiện.\n\n- **Ví dụ áp dụng K-G-Đ trong cuộc họp marketing:**\n  - Khen về sự sáng tạo và nghiên cứu xu hướng; góp ý về rủi ro chi phí và thiếu kinh nghiệm; đề xuất thử nghiệm nhỏ và nhờ chuyên gia hỗ trợ.  \n    Kết quả: Đối phương cảm thấy được tôn trọng, cùng hợp tác hoàn thiện.\n\n- **Ví dụ góp ý về thái độ/hiệu suất làm việc:**\n  - Khen về năng lực chuyên môn, nêu cụ thể vấn đề đi muộn/chậm deadline, đề xuất giải pháp hỗ trợ hoặc điều chỉnh timeline.  \n    Kết quả: Đồng nghiệp không cảm thấy bị chỉ trích cá nhân, đồng thuận cải thiện.\n\n---\n\n**4. Hướng dẫn & bước thực hiện**\n\n- **Để đặt câu hỏi thông minh:**\n  1. Luôn thể hiện thiện chí, dùng ngôn ngữ tôn trọng, tránh chất vấn, phán xét.\n  2. Hỏi thắng thắn nhưng không cá nhân hóa vấn đề, tránh đổ lỗi.\n  3. Mỗi câu hỏi chỉ tập trung vào một ý, chia nhỏ để dễ trả lời.\n  4. Sau khi nhận câu trả lời, tóm lược lại để xác nhận hiểu đúng.\n  5. Hỏi đủ thông tin, tránh sa đà vào tiểu tiết không cần thiết.\n  6. Biết dừng đúng lúc, chuyển sang hành động khi đã rõ.\n\n- **Áp dụng công thức Khen – Góp ý – Đề xuất (K-G-Đ):**\n  1. **Bước 1: Khen/ghi nhận điểm tốt**  \n     Chọn điểm sáng thực sự, khen cụ thể, tránh khen sáo rỗng.\n  2. **Bước 2: Góp ý xây dựng**  \n     Nêu điểm cần cải thiện một cách trung thực, rõ ràng, có dẫn chứng nếu có, tránh công kích cá nhân hay phán xét cảm tính.\n  3. **Bước 3: Đề xuất giải pháp**  \n     Đưa ra phương án cụ thể, khả thi; nếu chưa có phương án rõ, có thể hỏi thêm ý kiến đối phương.\n  4. **Cân nhắc bối cảnh & đối tượng:**  \n     Với sếp cần tinh tế, nhẹ nhàng hơn; với đồng nghiệp có thể thẳng thắn; với người mới nên tích cực động viên.\n\n- **Lưu ý khi thực hành:**\n  - Khen đúng điểm, tránh khen giả tạo.\n  - Góp ý cụ thể, tôn trọng, tránh mơ hồ, chỉ trích chung chung.\n  - Đề xuất hướng giải quyết rõ ràng, thực tế, mở cửa cho các phương án khác.\n  - Luôn giữ thái độ hợp tác, không biến phản biện thành tranh cãi.\n\n---\n\n**5. Điểm then chốt cần nhớ**\n\n1. **Đặt câu hỏi thông minh là nền tảng của phản biện tích cực, giúp làm rõ vấn đề, tiết kiệm thời gian và thể hiện sự tôn trọng.**\n2. **Công thức Khen – Góp ý – Đề xuất (K-G-Đ) là chìa khóa để phản biện mà không gây xung đột, thúc đẩy tinh thần hợp tác.**\n3. **Phản biện tích cực không chỉ là chỉ trích hay gật đầu đồng thuận, mà là nghệ thuật giao tiếp giúp hoàn thiện ý tưởng và nâng cao hiệu suất chung.**\n4. **Luôn căn cứ vào bối cảnh, thể hiện thái độ thiện chí, tôn trọng khi đặt câu hỏi hoặc đưa ra phản biện.**\n5. **Thực hành đều đặn hai kỹ năng cốt lõi này sẽ giúp bạn trở thành nhân tố tích cực, được đánh giá cao trong môi trường làm việc hiện đại.**"
    },
    {
      "index": 7,
      "title": "Chương 7: Tư duy phản biện trong việc giải quyết vấn đề và ra quyết định",
      "chapter_stem": "ch007_Chuong_7_Tu_duy_phan_bien_tron",
      "summary": "**Tóm tắt chương 7: Tư duy phản biện trong việc giải quyết vấn đề và ra quyết định**\n\n---\n\n**1. Luận điểm trung tâm**\n\nChương 7 nhấn mạnh rằng tư duy phản biện không chỉ dừng lại ở tranh luận, mà phải được sử dụng như một công cụ chủ động để giải quyết vấn đề và ra quyết định trong công việc, từ xử lý dự án chậm tiến độ, xung đột nội bộ, tới lựa chọn phương án đầu tư. Tác giả muốn người đọc phát triển năng lực tư duy phản biện đa chiều, biết phân tích dữ liệu, tìm gốc rễ vấn đề, đề xuất giải pháp có cơ sở và lộ trình rõ ràng, đồng thời dám quyết đoán, giảm sợ sai bằng cách luôn chuẩn bị kế hoạch dự phòng và thử nghiệm nhỏ trước khi triển khai rộng. Đây là kỹ năng rất được doanh nghiệp, lãnh đạo, đồng nghiệp đánh giá cao.\n\n---\n\n**2. Khái niệm & framework được giới thiệu**\n\n- **SWOT**: Phân tích 4 yếu tố: Strengths (điểm mạnh), Weaknesses (điểm yếu), Opportunities (cơ hội), Threats (rủi ro) để xây dựng bức tranh toàn cảnh, từ đó xác định hành động.\n  \n- **5 Why**: Kỹ thuật liên tục đặt câu hỏi “Tại sao?” 5 lần (hoặc đến khi chạm gốc rễ) để tìm nguyên nhân sâu xa của vấn đề, tránh chỉ xử lý phần nổi.\n\n- **6 chiếc mũ tư duy**: Mỗi “mũ” đại diện một góc nhìn: Trắng (dữ liệu), Đỏ (cảm xúc), Đen (rủi ro), Vàng (lợi ích), Xanh lá (sáng tạo), Xanh dương (điều phối, tổng hợp), nhằm đảm bảo phân tích đa chiều.\n\n- **Khen – Góp ý – Đề xuất**: Khung giao tiếp phản biện tích cực: bắt đầu bằng khen, sau đó góp ý về rủi ro/hạn chế, cuối cùng đề xuất giải pháp thay thế hoặc bổ sung kèm lập luận “Nếu – Thì – Bởi vì”.\n\n- **Plan B & thử nhỏ**: Luôn chuẩn bị phương án dự phòng và thử nghiệm quy mô nhỏ trước khi triển khai toàn diện để kiểm soát rủi ro.\n\n---\n\n**3. Ví dụ & câu chuyện thực tế**\n\n**Ví dụ 1: Phòng Marketing nâng doanh số online**\n- **Tình huống**: Phòng Marketing muốn tăng doanh số online.\n- **SWOT**:\n  - S: Giỏi Facebook Ads, có người biết Google Ads.\n  - W: Chưa rành TikTok Ads, thiếu content maker chuyên nghiệp.\n  - O: Gen Z thích TikTok, thị trường đang bùng nổ.\n  - T: Đối thủ mạnh về TikTok, chi ngân sách lớn.\n- **Kế hoạch**:\n  - Trích 15% ngân sách (~30 triệu) thử TikTok Ads trong 2 tuần.\n  - Thuê KOL tầm trung, training nội bộ về TikTok.\n  - Sau 2 tuần, đánh giá ROI: tốt thì tăng ngân sách, không thì quay về Facebook Ads.\n- **Bài học**: Phân tích rõ ràng, có thử nhỏ, có Plan B, tránh rủi ro lớn.\n\n**Ví dụ 2: Cá nhân muốn thăng tiến**\n- **Tình huống**: Một bạn muốn lên vị trí leader.\n- **SWOT**:\n  - S: Giỏi giao tiếp, từng tổ chức workshop.\n  - W: Thiếu bằng cấp quản trị, kém tiếng Anh.\n  - O: Công ty thiếu leader, sếp tìm người dẫn dắt.\n  - T: Sắp tái cơ cấu, nhiều ứng viên tiềm năng.\n- **Kế hoạch**:\n  - Đăng ký khoá quản trị cấp tốc.\n  - Đề xuất nhận thêm 1-2 task quản lý nhóm trong 2 tháng để thử sức.\n- **Bài học**: Chủ động tận dụng điểm mạnh, bổ sung điểm yếu trước khi bị “vượt mặt”.\n\n**Ví dụ 3: Giải quyết xung đột giữa phòng A và B bằng 5 Why**\n- **Tình huống**: Phòng A và B thường xuyên cãi nhau vì giao tài liệu trễ.\n- **Phân tích 5 Why**:\n  1. Vì B bảo A giao tài liệu trễ.\n  2. Vì A phải chờ sếp duyệt xong mới gửi.\n  3. Vì quy định bắt mọi văn bản phải có chữ ký sếp.\n  4. Vì trước đây từng có sai sót nên sếp muốn siết chặt.\n  5. Vì không ai dám đề xuất sửa quy định.\n- **Giải pháp**: Thống nhất tài liệu mức độ thấp A được tự quyết, không cần sếp duyệt.\n- **Bài học**: Gốc rễ không phải do cá nhân mà do quy trình cứng nhắc.\n\n**Ví dụ 4: Góp ý thay thế giải pháp trong cuộc họp**\n- **Tình huống**: Phòng kinh doanh muốn ra mắt đồng loạt nhiều tính năng, bạn (trưởng nhóm KT) lo ngại rủi ro kỹ thuật.\n- **Cách làm**: Áp dụng “Khen – Góp ý – Đề xuất”:\n  - Khen ý tưởng truyền thông mạnh.\n  - Góp ý về rủi ro code chưa ổn định, nêu số liệu về bug tăng nếu không kiểm thử kỹ.\n  - Đề xuất: Ra mắt 2-3 tính năng quan trọng trước, test kỹ, tuần sau mới ra mắt tiếp các tính năng còn lại.\n- **Bài học**: Đưa ra phản biện xây dựng, có số liệu, có giải pháp thay thế, được đánh giá cao.\n\n**Ví dụ 5: Nhận feedback**\n- **Tình huống**: Bị chê báo cáo rối, thiếu logic.\n- **Cách xử lý**: Hỏi rõ feedback, áp dụng 5 Why để tìm gốc rễ (do copy-paste, do chưa có số liệu KPI...), sửa đúng chỗ, cập nhật lại báo cáo, rút kinh nghiệm cho lần sau.\n- **Bài học**: Chủ động tiếp nhận, xử lý feedback, cải tiến liên tục.\n\n**Ví dụ 6: Sắp xếp ưu tiên khi đa nhiệm**\n- **Tình huống**: Có 5-7 tasks, ai cũng kêu gấp.\n- **Cách xử lý**: Liệt kê task, đánh giá mức độ quan trọng, khẩn cấp, khả năng ủy quyền; tập trung làm việc ưu tiên, ủy quyền hoặc lùi deadline hợp lý, thông báo rõ cho sếp/team.\n- **Bài học**: Chủ động kiểm soát công việc, không bị ngập việc, được đánh giá chuyên nghiệp.\n\n---\n\n**4. Hướng dẫn & bước thực hiện**\n\n**Quy trình chung áp dụng tư duy phản biện cho giải quyết vấn đề:**\n1. **Chọn phương pháp phân tích** phù hợp (SWOT, 5 Why, 6 mũ tư duy…).\n2. **Thu thập dữ liệu** (số liệu, ý kiến, phản hồi…).\n3. **Áp dụng kỹ thuật**: điền SWOT, đặt 5 Why, phân vai 6 mũ tư duy…\n4. **Đọc kết quả**, rút ra 2-3 điểm then chốt (điểm mạnh, rủi ro, nguyên nhân gốc…).\n5. **Chuyển thành hành động** (chọn phương án, sửa quy trình, đề xuất kế hoạch…).\n\n**Lưu ý**: Nên làm cùng các bên liên quan để có góc nhìn đa chiều.\n\n**Quy trình SWOT:**\n- Xác định chủ thể phân tích (dự án, cá nhân, phòng ban…).\n- Chuẩn bị 4 cột: S, W, O, T, ghi cụ thể, có số liệu.\n- Thảo luận nhóm hoặc tự phản biện: kết hợp S+O tận dụng lợi thế; W+T cần xử lý gấp.\n- Viết kế hoạch hành động cụ thể (ai làm gì, thời hạn).\n- Trình bày báo cáo theo mẫu “Khen – Góp ý – Đề xuất” để tránh tranh cãi.\n\n**Quy trình 5 Why:**\n- Xác định hiện tượng/vấn đề bề mặt.\n- Đặt câu hỏi “Tại sao?” và ghi nhận câu trả lời.\n- Lặp lại đến khi tìm ra nguyên nhân sâu nhất.\n- Đưa giải pháp xử lý tận gốc.\n- Lưu ý: Không dùng để quy trách cá nhân, nên tập trung vào quy trình/cơ chế.\n\n**6 chiếc mũ tư duy:**\n- Nêu rõ chủ đề cần bàn.\n- Phân vai từng người theo 6 mũ, hoặc lần lượt đổi góc nhìn.\n- Đảm bảo mọi khía cạnh (dữ liệu, cảm xúc, rủi ro, lợi ích, sáng tạo, điều phối) đều được phân tích.\n\n**Khen – Góp ý – Đề xuất trong góp ý:**\n- Khen điểm tốt của phương án.\n- Góp ý chỉ ra hạn chế, rủi ro, có số liệu dẫn chứng.\n- Đề xuất giải pháp thay thế, trình bày rõ logic “Nếu – Thì – Bởi vì”.\n\n**Khi ra quyết định hoặc triển khai phương án:**\n- Luôn chuẩn bị Plan B (kịch bản dự phòng).\n- Triển khai thử nhỏ (10-20% quy mô), theo dõi KPI để quyết bung rộng hay rút lui.\n- Truyền thông rõ ràng với team/sếp về rủi ro và phương án dự phòng để chia sẻ trách nhiệm.\n\n**Quản lý đa nhiệm:**\n- Liệt kê tasks, đánh giá deadline, mức độ quan trọng, khả năng ủy quyền.\n- Sắp xếp thứ tự ưu tiên, phân bổ người thực hiện, thông báo rõ cho team/sếp.\n\n---\n\n**5. Điểm then chốt cần nhớ**\n\n1. **Tư duy phản biện hiệu quả là phân tích đa chiều, đào sâu nguyên nhân, đưa ra giải pháp có cơ sở và lộ trình rõ ràng, không chỉ dừng lại ở phản bác ý kiến.**\n2. **Các công cụ như SWOT, 5 Why, 6 chiếc mũ tư duy giúp bạn nhìn nhận vấn đề toàn diện, tránh phiến diện, xử lý tận gốc rễ thay vì chỉ sửa phần nổi.**\n3. **Kỹ năng phản biện tích cực (Khen – Góp ý – Đề xuất) giúp bạn xây dựng thay vì đối đầu, nâng cao giá trị bản thân trong mắt lãnh đạo và đồng nghiệp.**\n4. **Luôn chuẩn bị Plan B và thử nhỏ để giảm rủi ro, dám ra quyết định mà không sợ sai, vì đã có phương án dự phòng.**\n5. **Chủ động tiếp nhận và xử lý feedback, biết ưu tiên công việc theo logic giúp bạn làm việc chuyên nghiệp, kiểm soát hiệu quả và thăng tiến dễ dàng trong môi trường cạnh tranh.**"
    },
    {
      "index": 8,
      "title": "Đáp án",
      "chapter_stem": "ch008_ap_an",
      "summary": "**1. Luận điểm trung tâm**  \nChương “Đáp án” chủ yếu cung cấp toàn bộ lời giải (đáp án) cho các câu hỏi trắc nghiệm hoặc bài tập xuất hiện trong sách. Mục đích của chương là giúp người đọc đối chiếu, kiểm tra kết quả làm bài, tự đánh giá mức độ hiểu bài và phát hiện các lỗi sai để tự học hiệu quả hơn. Chương này không nhằm thuyết phục hay giảng giải kiến thức mới mà tập trung làm rõ và xác nhận các đáp án chính xác cho từng câu hỏi đã được đưa ra trước đó trong sách.\n\n**2. Khái niệm & framework được giới thiệu**  \nChương này không giới thiệu khái niệm, mô hình hay framework mới nào. Nội dung chỉ bao gồm danh sách đáp án cho từng câu hỏi, không giải thích về cách làm hay lý thuyết liên quan.\n\n**3. Ví dụ & câu chuyện thực tế**  \nChương “Đáp án” không đưa ra bất cứ ví dụ, case study hay câu chuyện thực tế nào. Nội dung hoàn toàn là liệt kê đáp án trắc nghiệm dưới dạng mã số câu hỏi kèm đáp án tương ứng (ví dụ: 1A, 2B, 3C...).\n\n**4. Hướng dẫn & bước thực hiện**  \nTuy không có hướng dẫn trực tiếp trong chương, nhưng về bản chất, chương này phục vụ cho quy trình tự kiểm tra kết quả học tập như sau:\n\n- Bước 1: Người đọc hoàn thành các câu hỏi/bài tập trong sách mà không xem đáp án trước.\n- Bước 2: Sau khi làm xong, đối chiếu câu trả lời của mình với bảng đáp án trong chương “Đáp án”.\n- Bước 3: Đánh dấu những câu trả lời đúng và sai.\n- Bước 4: Ôn lại lý thuyết hoặc xem lại bài học với những câu trả lời sai để củng cố kiến thức.\n- Bước 5: Lặp lại quá trình làm bài – kiểm tra – ôn tập nếu cần nâng cao kỹ năng.\n\n**5. Điểm then chốt cần nhớ**\n1. Chương “Đáp án” liệt kê đầy đủ, chính xác đáp án cho mọi câu hỏi/bài tập trong sách.\n2. Mục tiêu của chương là giúp người học tự đánh giá kết quả, xác định lỗi sai và củng cố kiến thức.\n3. Không có lý thuyết, ví dụ minh họa hay giải thích phương pháp giải trong chương này.\n4. Người học cần làm bài độc lập trước khi đối chiếu đáp án để đạt hiệu quả cao nhất.\n5. Đáp án chỉ là công cụ kiểm tra, việc hiểu sâu lý do đúng/sai của từng lựa chọn vẫn cần tham khảo thêm lý thuyết hoặc phần giải thích (nếu có trong các chương khác)."
    }
  ],
  "full_summary": "## Giới thiệu cuốn sách\n\nCuốn sách này tập trung vào một trong những kỹ năng quan trọng nhất của thế kỷ 21: **tư duy phản biện**. Ở thời đại bùng nổ thông tin, mạng xã hội phát triển, tin giả, lừa đảo và thao túng cảm xúc diễn ra khắp nơi, khả năng suy nghĩ độc lập, phân tích, đánh giá và ra quyết định sáng suốt trở thành tấm khiên bảo vệ cá nhân, đồng thời là chìa khóa thành công trong học tập, nghề nghiệp và đời sống.\n\n**Luận điểm xuyên suốt** của cuốn sách là: Tư duy phản biện không chỉ là kỹ năng phòng vệ, mà còn là nền tảng cho sáng tạo, hợp tác, đổi mới – giúp mỗi người trở thành phiên bản tốt hơn, đóng góp tích cực cho tập thể và xã hội.\n\n**Đối tượng độc giả lý tưởng** gồm:  \n- Học sinh, sinh viên muốn tự học, tự bảo vệ mình trước “bẫy” thông tin, rèn luyện kỹ năng học tập chủ động.\n- Người đi làm, đặc biệt là những ai muốn nổi bật trong mắt nhà tuyển dụng, lãnh đạo, và xây dựng sự nghiệp bền vững.\n- Các nhà quản lý, lãnh đạo mong muốn tạo ra môi trường làm việc sáng tạo, minh bạch, và tăng hiệu suất đội nhóm.\n- Bất kỳ ai mong muốn ra quyết định sáng suốt, giao tiếp hiệu quả, phòng tránh rủi ro trong đời sống số.\n\nCuốn sách không chỉ dừng lại ở lý thuyết mà còn cung cấp mô hình thực tiễn, ví dụ đời thường, hướng dẫn rèn luyện từng ngày và lộ trình ứng dụng tư duy phản biện trong cả học tập lẫn công việc.\n\n---\n\n## Nội dung theo từng phần/chủ đề lớn\n\n### 1. Bản chất tư duy phản biện: Nhận diện và xây dựng nền tảng\n\n#### Ý tưởng chính\nTư duy phản biện là quá trình phân tích, đánh giá, so sánh và giải thích các vấn đề một cách khách quan, có hệ thống. Nó khác hoàn toàn với việc phản đối hay phê bình đơn thuần. Mục đích của phản biện là xây dựng, hoàn thiện, không phải để tranh cãi, bác bỏ hoặc thể hiện bản thân.\n\n#### Ví dụ/câu chuyện tiêu biểu\nNgụ ngôn “Những người mù sờ voi” cho thấy mỗi người chỉ nắm một phần của sự thật. Nếu không có tư duy phản biện để phân tích, tổng hợp và lắng nghe, mọi người dễ rơi vào tranh cãi vô bổ, không bao giờ chạm tới bản chất của vấn đề.\n\nTrong đời sống hiện đại, các quyết định như chọn ngành học, mua điện thoại, đánh giá quảng cáo hay phòng tránh lừa đảo đều đòi hỏi kiểm tra, phân tích thông tin từ nhiều chiều. Văn hóa phản biện ở Israel hay các nước phương Tây phát triển mạnh nhờ khuyến khích đặt câu hỏi, tranh luận từ nhỏ đến trong môi trường doanh nghiệp.\n\n#### Điểm then chốt\n- **Phản biện** là nền tảng của nhận thức khách quan, giúp phân tích đa chiều, tìm ra giải pháp tối ưu.\n- Bốn bước nền tảng: **Phân tích – Đánh giá – So sánh – Giải thích**.\n- Cần phân biệt rõ giữa “phản biện” (xây dựng), “phản đối” (bác bỏ, tiêu cực), “phê bình” (chỉ trích điểm yếu).\n- Tư duy phản biện giúp tránh bị thao túng, ra quyết định sáng suốt và xây dựng văn hóa hợp tác, sáng tạo.\n\n---\n\n### 2. Công cụ nhận diện bẫy tư duy và đánh giá thiếu chính xác\n\n#### Ý tưởng chính\nTrong thời đại số, con người dễ rơi vào các bẫy tư duy khiến đánh giá thông tin sai lệch, hành động bốc đồng hoặc chia sẻ thiếu kiểm chứng. Để phòng vệ, cần nhận diện các bẫy này và áp dụng Quy tắc 3C để xác thực thông tin.\n\n#### Ví dụ/câu chuyện tiêu biểu\nCâu chuyện “con gà đẻ trứng vàng” minh họa cho nhiều bẫy nhận thức: lòng tham, hiệu ứng hào quang, đám đông... dẫn đến lựa chọn sai lầm với hậu quả lớn.\n\nNhững trường hợp nhận email trúng thưởng, quảng cáo bảo hiểm giá rẻ hay video cắt ghép đều là môi trường lý tưởng để thực hành Quy tắc 3C: **Kiểm tra nguồn – So sánh nhiều nguồn – Đặt vào bối cảnh**.\n\n#### Điểm then chốt\n- Các bẫy tư duy như: **hiệu ứng hào quang, xác nhận thiên kiến, tin giật gân, FOMO, neo tâm lý, bẫy đám đông**… khiến ta đánh giá sai.\n- **Quy tắc 3C** là bộ lọc thực tiễn, giúp kiểm tra tính xác thực của thông tin.\n- Luyện tập 3C giúp chủ động sàng lọc, tránh bị thao túng, không ra quyết định/chia sẻ chỉ dựa vào cảm xúc hoặc đám đông.\n- Thực hành 3C thường xuyên giúp rèn kỹ năng phản biện vững chắc.\n\n---\n\n### 3. Bảo vệ cảm xúc – Đừng để bị dắt mũi\n\n#### Ý tưởng chính\nCảm xúc là mảnh đất màu mỡ cho các chiêu thức thao túng trên mạng xã hội, quảng cáo, lừa đảo… Nếu không kiểm soát, con người dễ bị dắt mũi, đưa ra quyết định vội vàng, gây hậu quả nghiêm trọng cho bản thân và tập thể.\n\n#### Ví dụ/câu chuyện tiêu biểu\nNam – một người dùng mạng xã hội – bị lôi kéo vào tranh cãi, mất thời gian, ảnh hưởng tâm trạng chỉ vì bị kích động cảm xúc. Nhiều người bị lừa đảo qua điện thoại giả danh công an, người thân gặp nạn, bị dẫn dắt vào đầu tư đa cấp, mua hàng không cần thiết chỉ vì chiêu trò đánh vào cảm xúc tội lỗi, sợ hãi, lòng tham.\n\n#### Điểm then chốt\n- Não bộ ưu tiên cảm xúc, khiến hành động bốc đồng khi bị kích động.\n- Có nhiều chiêu trò thao túng cảm xúc trên môi trường số, như tin nhắn cảnh báo, video gây sốc, khuyến mãi “giờ vàng”…\n- **Kỹ thuật phanh cảm xúc 10 giây**, **checklist kiểm chứng 5 bước**, **bản đồ 3 điểm vượt rừng cảm xúc (A-B-C)** giúp nhận diện, kiểm soát, chủ động bảo vệ bản thân.\n- Rèn luyện kiểm soát cảm xúc là kỹ năng thiết yếu, góp phần thành công và an toàn lâu dài.\n\n---\n\n### 4. Phòng vệ trước tin giả và lừa đảo\n\n#### Ý tưởng chính\nTin giả và lừa đảo trực tuyến ngày càng phát triển, tinh vi và khó nhận biết. Ai cũng có thể là nạn nhân nếu thiếu tư duy phản biện, kỹ năng kiểm chứng. Phòng vệ chủ động đòi hỏi xây dựng thói quen xác thực thông tin, cảnh giác, sử dụng các công cụ và kỹ thuật số hiện đại.\n\n#### Ví dụ/câu chuyện tiêu biểu\nCâu chuyện “Cậu bé chăn cừu” cho thấy hậu quả nghiêm trọng khi tin giả, thông tin sai lệch lan rộng. Tin đồn về COVID-19, các doanh nghiệp bị vu oan, thông tin giả về vắc-xin, lừa đảo email ngân hàng, deepfake video call… là những ví dụ điển hình của thời đại số.\n\n#### Điểm then chốt\n- Tin giả/lừa đảo là hiểm họa thực sự, không ai miễn nhiễm.\n- Nhận diện dấu hiệu: tiêu đề giật gân, thiếu nguồn, cảm tính, ép chia sẻ, ảnh/video mập mờ.\n- Áp dụng các bước kiểm chứng: kiểm tra nguồn, đối chiếu, dùng công cụ fact-check, hỏi chuyên gia.\n- **Suy nghĩ chậm**, **tạm dừng 10 giây** khi gặp thông tin khiến cảm xúc mạnh.\n- Giáo dục bản thân, nâng kỹ năng số, lan tỏa văn hóa kiểm chứng là cách bảo vệ lâu dài nhất.\n\n---\n\n### 5. Tư duy phản biện – “điểm cộng” trong mắt nhà tuyển dụng\n\n#### Ý tưởng chính\nTrong môi trường làm việc hiện đại, tư duy phản biện là kỹ năng mềm được các nhà tuyển dụng săn đón. Người biết phản biện không chỉ hoàn thành nhiệm vụ mà còn chủ động cải tiến, giải quyết vấn đề, thúc đẩy đổi mới và đóng góp cho văn hóa doanh nghiệp.\n\n#### Ví dụ/câu chuyện tiêu biểu\nGoogle nổi tiếng với văn hóa khuyến khích đặt câu hỏi, nhờ đó tạo ra nhiều sản phẩm đột phá. Các startup Việt thành công nhờ nhân sự chủ động phản biện để đổi mới. Trong phỏng vấn, ứng viên biết đặt câu hỏi, phân tích đa chiều thường gây ấn tượng mạnh với nhà tuyển dụng.\n\nCác case thực tế: bán lẻ, nhà hàng, may mặc, xây dựng, agency… đều cho thấy đội ngũ biết phản biện giúp doanh nghiệp cải tiến, kiểm soát rủi ro, phát triển bền vững.\n\n#### Điểm then chốt\n- Tư duy phản biện là “điểm cộng” nổi bật cho ứng viên.\n- Phản biện không phải để đối đầu, mà để xây dựng, hoàn thiện.\n- Nhân sự phản biện giúp giải quyết vấn đề tận gốc, đổi mới, kiểm soát rủi ro.\n- Văn hóa phản biện tăng gắn kết, minh bạch, phát huy sức mạnh tập thể.\n- Rèn luyện tư duy phản biện càng sớm càng tốt để trở thành nhân tố sáng giá trên thị trường lao động.\n\n---\n\n### 6. Kỹ năng phản biện tích cực trong môi trường làm việc\n\n#### Ý tưởng chính\nPhản biện tích cực là nghệ thuật đặt câu hỏi thông minh, góp ý xây dựng và đề xuất giải pháp, giúp tăng hiệu quả hợp tác, làm việc nhóm và hoàn thiện ý tưởng, sản phẩm.\n\n#### Ví dụ/câu chuyện tiêu biểu\nMột dự án thất bại do không hỏi rõ ngân sách, dẫn đến phải làm lại. Trong họp, người đặt câu hỏi mục tiêu giúp cả đội hiểu rõ định hướng, tránh lãng phí thời gian. Khi góp ý theo công thức **Khen – Góp ý – Đề xuất (K-G-Đ)**, đồng nghiệp dễ tiếp nhận, cải thiện hiệu quả, tăng gắn kết.\n\n#### Hướng dẫn thực hiện\n- **Đặt câu hỏi thông minh:** Luôn xuất phát từ thiện chí, tôn trọng, tập trung vào một ý, xác nhận lại, tránh sa đà tiểu tiết.\n- **K-G-Đ:** Khen cụ thể điểm tốt; góp ý xây dựng, có dẫn chứng; đề xuất giải pháp rõ ràng, dễ thử nghiệm; cân nhắc đối tượng, luôn giữ thái độ hợp tác.\n\n#### Điểm then chốt\n- Đặt câu hỏi thông minh và K-G-Đ là bộ đôi nền tảng của phản biện tích cực.\n- Giúp hoàn thiện ý tưởng, tăng hiệu suất, giữ hợp tác, tránh mâu thuẫn không cần thiết.\n- Luôn xét bối cảnh, thực hành đều đặn để trở thành nhân tố tích cực trong công việc.\n\n---\n\n### 7. Tư duy phản biện trong giải quyết vấn đề và ra quyết định\n\n#### Ý tưởng chính\nTư duy phản biện là công cụ chủ động để giải quyết vấn đề, ra quyết định thông minh. Nó giúp phân tích đa chiều, tìm nguyên nhân gốc, đề xuất giải pháp có cơ sở, chuẩn bị phương án dự phòng và thử nghiệm nhỏ, tăng khả năng thành công và được đánh giá cao trong công việc.\n\n#### Ví dụ/câu chuyện tiêu biểu\nPhòng Marketing thử kênh TikTok Ads dựa trên phân tích SWOT và có Plan B phòng khi không hiệu quả. Một nhân viên muốn lên vị trí leader sử dụng SWOT để tận dụng điểm mạnh, khắc phục điểm yếu, từ đó lập kế hoạch học tập. Khi có sự cố, nhóm dùng **5 Why** để tìm nguyên nhân gốc, sửa quy trình, tránh lặp lại lỗi. Trong họp kinh doanh, áp dụng K-G-Đ để góp ý kỹ thuật, giúp giải quyết xung đột phòng ban. Quản lý đa nhiệm bằng cách liệt kê, ưu tiên, ủy quyền công việc.\n\n#### Hướng dẫn thực hiện\n- **Chọn phương pháp phân tích phù hợp:** SWOT cho tổng thể, 5 Why để tìm nguyên nhân, 6 mũ tư duy để phân tích đa chiều.\n- **K-G-Đ:** Góp ý xây dựng rõ ràng, có dẫn chứng, đề xuất thay thế.\n- **Quy trình ra quyết định:** Luôn có Plan B, thử nghiệm nhỏ trước khi nhân rộng, truyền thông rõ ràng với đội nhóm.\n- **Quản lý đa nhiệm:** Liệt kê, đánh giá, sắp xếp ưu tiên, ủy quyền hợp lý.\n\n#### Điểm then chốt\n- Tư duy phản biện là phân tích đa chiều, giải pháp có cơ sở, lộ trình rõ.\n- Kết hợp nhiều công cụ: SWOT, 5 Why, 6 mũ tư duy, K-G-Đ.\n- Luôn chủ động chuẩn bị phương án dự phòng, thử nhỏ để giảm rủi ro.\n- Chủ động nhận feedback, ưu tiên công việc giúp làm việc chuyên nghiệp.\n\n---\n\n### 8. Đáp án – Củng cố, tự kiểm tra, hoàn thiện kỹ năng\n\n#### Ý tưởng chính\nChương này cung cấp đáp án cho các bài tập/trắc nghiệm giúp bạn tự kiểm tra, đánh giá mức độ hiểu và củng cố kiến thức. Không có thêm lý thuyết hay ví dụ mới.\n\n#### Hướng dẫn thực hiện\n- Làm bài tập độc lập trước, sau đó đối chiếu đáp án.\n- Đánh dấu đúng/sai, xem lại lý thuyết ở các chương trước với những câu sai.\n- Lặp lại quá trình để ghi nhớ và hoàn thiện kỹ năng.\n\n#### Điểm then chốt\n- Đáp án chỉ là công cụ kiểm tra, quan trọng là hiểu lý do đúng/sai, nắm vững mô hình, kỹ thuật đã học.\n\n---\n\n## Các khái niệm & framework cốt lõi\n\n### 1. **Khái niệm tư duy phản biện**\nLà quá trình sử dụng lý trí để phân tích, đánh giá, so sánh và giải thích vấn đề một cách khách quan, toàn diện, có mục đích xây dựng, cải tiến. Không phải phản đối hay phê phán tiêu cực.\n\n### 2. **4 bước nền tảng của tư duy phản biện**\n- **Phân tích:** Tách nhỏ vấn đề, tìm hiểu từng phần.\n- **Đánh giá:** Xác định điểm mạnh, yếu, giá trị, rủi ro.\n- **So sánh:** Đối chiếu giữa các phương án, nguồn, trải nghiệm.\n- **Giải thích:** Diễn giải, trình bày lại bằng ngôn ngữ của mình, tổng hợp thành hiểu biết chung.\n\n### 3. **Quy tắc 3C** (Kiểm tra – So sánh – Đặt vào bối cảnh)\n- **Kiểm tra nguồn:** Ai phát ra thông tin này? Độ tin cậy ra sao?\n- **So sánh nhiều nguồn:** Có nguồn nào khác nói giống vậy không?\n- **Đặt vào bối cảnh:** Thông tin này hợp lý ở tình huống, thời điểm, địa điểm nào? Có mâu thuẫn gì không?\n\n### 4. **Các bẫy tư duy phổ biến**\n- **Hiệu ứng hào quang:** Đánh giá toàn diện chỉ dựa vào một đặc điểm nổi bật.\n- **Xác nhận thiên kiến:** Chỉ tìm bằng chứng củng cố niềm tin sẵn có.\n- **FOMO:** Sợ bỏ lỡ cơ hội, dẫn đến hành động vội vàng.\n- **Bẫy đám đông:** Làm theo đa số mà không kiểm chứng.\n- **Neo tâm lý:** Bị “móc neo” vào một thông tin, giá trị ban đầu và thiếu linh hoạt thay đổi.\n- **Tin giật gân:** Bị cuốn theo tiêu đề, hình ảnh sốc mà bỏ qua kiểm chứng.\n\n### 5. **Kỹ thuật kiểm soát cảm xúc**\n- **Phanh cảm xúc 10 giây:** Dừng lại, thở sâu, đếm 10 giây trước khi phản ứng với bất kỳ thông tin gây sốc, giận dữ, vui sướng quá mức.\n- **Checklist kiểm chứng 5 bước:** Nguồn – Bằng chứng – Đối chiếu – Động cơ – Hành động sau dừng lại.\n- **Bản đồ 3 điểm vượt rừng cảm xúc (A-B-C):** Nhận diện cảm xúc, xác định đối tượng thao túng, đưa ra hướng giải quyết.\n\n### 6. **Phòng vệ trước tin giả/lừa đảo**\n- **Nhận diện dấu hiệu:** Tiêu đề giật gân, thiếu nguồn, dùng cảm xúc mạnh, ép chia sẻ, nội dung mập mờ, hình ảnh/video khả nghi.\n- **Kiểm chứng:** Dùng các trang fact-check, kiểm tra hình ảnh/video, hỏi chuyên gia, đối chiếu nhiều nguồn.\n- **Suy nghĩ chậm, tạm dừng 10 giây** trước khi lan truyền hoặc ra quyết định.\n\n### 7. **Phản biện xây dựng – công thức Khen – Góp ý – Đề xuất (K-G-Đ)**\n- **Khen:** Nhận diện, công nhận điểm tốt, cụ thể của đối tượng.\n- **Góp ý:** Chỉ ra điểm hạn chế, rủi ro, có dẫn chứng rõ ràng.\n- **Đề xuất:** Đưa ra giải pháp cụ thể, dễ thực hiện, thử nhỏ trước.\n\n### 8. **Các công cụ giải quyết vấn đề**\n- **SWOT:** Phân tích điểm mạnh – yếu – cơ hội – rủi ro.\n- **5 Why:** Hỏi liên tục “tại sao?” để tìm nguyên nhân gốc rễ.\n- **6 chiếc mũ tư duy:** Phân tích đa góc nhìn: dữ liệu, cảm xúc, rủi ro, lợi ích, sáng tạo, điều phối.\n- **Plan B & thử nhỏ:** Luôn chuẩn bị phương án dự phòng, thử nghiệm trước khi mở rộng.\n\n---\n\n## Bài học thực tiễn\n\n### 1. **Rèn luyện tư duy phản biện hàng ngày**\n- **Đặt câu hỏi** khi tiếp nhận thông tin: Ai nói? Nguồn ở đâu? Mục đích gì?\n- **Phân tích đa chiều** mọi vấn đề: Đừng chỉ tin vào cảm giác đầu tiên hoặc ý kiến đám đông.\n- **Giải thích lại** bằng ngôn ngữ của mình để kiểm tra hiểu đúng bản chất.\n\n### 2. **Thực hành Quy tắc 3C**\n- Khi nhận tin nhắn, quảng cáo, tin tức: kiểm tra nguồn, so sánh với các nguồn khác, đặt trong bối cảnh.\n- Không chia sẻ, ra quyết định khi chưa thực hiện đủ 3 bước.\n\n### 3. **Kiểm soát cảm xúc trước thông tin số**\n- Khi cảm thấy kích động (giận dữ, vui mừng quá mức, lo lắng...), hãy **dừng lại 10 giây**, hít thở sâu, tự hỏi: “Có thể ai đó đang cố làm mình mất kiểm soát không?”\n- Dùng checklist 5 bước và bản đồ 3 điểm để nhận diện sự thao túng, tự chủ cảm xúc.\n\n### 4. **Phòng vệ trước tin giả, lừa đảo**\n- Nhận diện các dấu hiệu bất thường, không vội tin thông tin gây sốc, giật gân, hạn sử dụng gấp.\n- Kiểm tra nguồn qua các trang như Google, Snopes, các công cụ fact-check hình ảnh/video.\n- Khi nghi ngờ, hỏi ý kiến chuyên gia hoặc người có kinh nghiệm.\n\n### 5. **Ứng dụng phản biện trong công việc**\n- **Đặt câu hỏi thông minh** trong họp, giao việc, nhận dự án để xác định mục tiêu, rủi ro, nguồn lực.\n- **Góp ý, phản biện theo K-G-Đ** để xây dựng, không gây mâu thuẫn.\n- **Phân tích vấn đề bằng SWOT, 5 Why, 6 mũ tư duy** để tìm nguyên nhân và giải pháp toàn diện.\n- **Luôn có Plan B, thử nghiệm nhỏ** trước khi mở rộng quy mô.\n- **Chủ động nhận feedback, ưu tiên công việc, ủy quyền hợp lý** để làm việc chuyên nghiệp.\n\n### 6. **Tự kiểm tra, củng cố kiến thức**\n- Làm bài tập, trắc nghiệm, tự đánh giá, xem lại lý thuyết với những điểm chưa chắc.\n- Lặp lại quá trình cho đến khi thực sự hiểu và ứng dụng được.\n\n---\n\n## Kết luận\n\n**Giá trị cốt lõi** của cuốn sách là: Mỗi cá nhân đều có thể và cần phải rèn luyện tư duy phản biện để tự phòng vệ trong thời đại số, đồng thời chủ động phát triển bản thân, đóng góp cho tập thể và xã hội.\n\nTư duy phản biện không phải là đặc quyền của một số ít người “giỏi tranh luận”, mà là kỹ năng nền tảng mọi người cần có:  \n- Để nhận diện, phân tích, đánh giá vấn đề khách quan, tránh bị thao túng, lừa đảo;\n- Để kiểm soát cảm xúc, ra quyết định sáng suốt trong học tập, nghề nghiệp, đời sống số;\n- Để trở thành nhân sự nổi bật, xây dựng văn hóa doanh nghiệp sáng tạo, hợp tác, minh bạch;\n- Để giải quyết vấn đề, cải tiến, đổi mới với các công cụ thực tiễn như 3C, K-G-Đ, SWOT, 5 Why, 6 mũ tư duy…\n\nTác động lớn nhất mà cuốn sách có thể tạo ra:  \n- Giúp mỗi người xây dựng “bộ lọc” phòng vệ trước thông tin sai, bảo vệ bản thân, gia đình, cộng đồng;\n- Tăng cường tính độc lập, chủ động, sáng tạo, khả năng hợp tác – những năng lực thiết yếu của công dân toàn cầu;\n- Góp phần lan tỏa văn hóa phản biện tích cực, xây dựng xã hội minh bạch, văn minh, phát triển bền vững.\n\n**Kết lại:**  \nTư duy phản biện không phải điều xa vời, mà là kỹ năng có thể rèn luyện từng ngày. Hãy bắt đầu từ hôm nay – đặt câu hỏi, kiểm chứng thông tin, kiểm soát cảm xúc, phản biện xây dựng – để trở thành phiên bản tốt hơn của chính mình, đồng thời góp phần tạo dựng môi trường, xã hội an toàn, tiến bộ."
}