{
  "book_name": "8f592ec1-ab81-45f7-a8f9-4a8488656256_SHS.L05.S332_vn_unpublished",
  "id": "8f592ec1-ab81-45f7-a8f9-4a8488656256",
  "sku": "SHS.L05.S332",
  "title": "Mindmap kiến thức Toán Văn Anh lớp 5 - Chi tiết, dễ hiểu, sát chương trình mới!",
  "market": "vn",
  "language": "vi",
  "has_toc": true,
  "chapters": [
    {
      "index": 1,
      "title": "Toán",
      "chapter_stem": "ch001_Toan",
      "summary": "**Tóm tắt chương \"Toán\" (theo chuẩn CliffsNotes)**\n\n---\n\n### 1. Luận điểm trung tâm\n\nChương \"Toán\" cung cấp kiến thức nền tảng và các kỹ năng cơ bản về số học, đại lượng đo lường, hình học, thống kê và xác suất cho học sinh tiểu học. Tác giả hướng dẫn cách nhận diện, đọc, viết, chuyển đổi, so sánh, tính toán với các dạng số (phân số, số thập phân, hỗn số), thực hiện các phép toán cơ bản, hiểu và vận dụng các khái niệm về tỉ số, tỉ số phần trăm, đo lường, các loại hình phẳng và hình khối, đồng thời giới thiệu bước đầu về thống kê và xác suất. Chuỗi kiến thức này trang bị cho học sinh những nền tảng toán học cần thiết để giải quyết các bài toán thực tế và phát triển tư duy logic.\n\n---\n\n### 2. Khái niệm & framework được giới thiệu\n\n**A. Số học**\n\n- **Phân số thập phân:** Phân số có mẫu số là 10, 100, 1000,...\n- **Hỗn số:** Tổng của một số tự nhiên và một phân số bé hơn 1, gồm phần nguyên và phần phân số.\n- **Số thập phân:** Số có phần nguyên và phần thập phân, phân cách bởi dấu phẩy.\n- **Tỉ số:** Thương của hai số, ký hiệu a : b hoặc $\\frac{a}{b}$.\n- **Tỉ số phần trăm:** Tỉ số có mẫu số 100, ký hiệu %.\n- **Làm tròn số thập phân:** Quy tắc làm tròn đến hàng đơn vị, phần mười, phần trăm...\n\n**B. Hình học và đo lường**\n\n- **Hình tam giác:** Các loại tam giác (nhọn, vuông, tù, đều), khái niệm đáy, đường cao, diện tích $S = \\frac{a \\times h}{2}$.\n- **Hình thang:** Đặc điểm, đáy, đường cao, diện tích $S = \\frac{(a + b) \\times h}{2}$.\n- **Hình tròn:** Bán kính, đường kính, chu vi $C = d \\times 3,14$ hoặc $C = 2r \\times 3,14$, diện tích $S = r \\times r \\times 3,14$.\n- **Hình lập phương:** Diện tích xung quanh $S_{xq} = a \\times a \\times 4$, diện tích toàn phần $S_{tp} = a \\times a \\times 6$, thể tích $V = a \\times a \\times a$.\n- **Hình hộp chữ nhật:** Diện tích xung quanh $S_{xq} = (a + b) \\times 2 \\times h$, diện tích toàn phần $S_{tp} = S_{xq} + 2ab$, thể tích $V = a \\times b \\times h$.\n- **Đơn vị đo diện tích, thể tích, thời gian:** Hệ thống chuyển đổi giữa các đơn vị.\n\n**C. Thống kê & Xác suất**\n\n- **Biểu diễn số liệu:** Bảng, biểu đồ cột, biểu đồ hình quạt.\n- **Xác suất thực nghiệm:** $P(A) = \\frac{\\text{số lần A xảy ra}}{\\text{tổng số lần thử}}$.\n- **Các trường hợp xác suất:** Sự kiện chắc chắn (P=1), không thể (P=0), độc lập, phụ thuộc.\n\n---\n\n### 3. Ví dụ & câu chuyện thực tế\n\n**A. Số học**\n\n- **Chuyển đổi phân số thành phân số thập phân:**\n    - $\\frac{1}{2} = \\frac{5}{10}$ bằng cách nhân cả tử và mẫu với 5.\n    - $\\frac{84}{200} = \\frac{42}{100}$ bằng cách chia cả tử và mẫu cho 2.\n\n- **Chuyển đổi hỗn số và phân số:**\n    - $3 \\frac{5}{4} = \\frac{17}{4}$ theo công thức $(3 \\times 4) + 5 = 17$.\n    - Chuyển $\\frac{32}{10}$ thành hỗn số: $32 : 10 = 3$, dư 2, kết quả $3 \\frac{2}{10}$.\n\n- **So sánh số thập phân:**\n    - $123,01 > 118,23$ do phần nguyên 123 > 118.\n    - $29,356 > 29,23$ vì phần nguyên bằng nhau, phần thập phân 3 > 2 ở hàng phần mười.\n    - $3,567 = 3,567$ vì các chữ số đều bằng nhau.\n\n- **Làm tròn số thập phân:**\n    - $7,39 \\rightarrow 7$ (phần mười <5).\n    - $5,63 \\rightarrow 6$ (phần mười ≥5).\n    - $3,204 \\rightarrow 3,2$ (phần trăm <5).\n    - $4,560 \\rightarrow 4,6$ (phần trăm ≥5).\n\n- **Phép tính với số thập phân:**\n    - $23,16 + 12,07 = 35,23$, đặt tính thẳng hàng, dấu phẩy thẳng cột.\n    - $45,07 - 23,19 = 21,88$.\n    - $35,6 \\times 100 = 3560$ (dịch dấu phẩy 2 chữ số).\n    - $239,3 \\times 0,1 = 23,93$ (dịch dấu phẩy sang trái 1 chữ số).\n    - $43,12 : 10 = 4,312$ (dịch dấu phẩy sang trái 1 chữ số).\n    - $43,12 : 0,1 = 431,2$ (dịch dấu phẩy sang phải 1 chữ số).\n\n- **Bài toán tỉ số (tìm hai số khi biết tổng và tỉ số):**\n    - Tổng 48, tỉ số 3:5. $3+5=8$ phần, số bé $=48:8\\times3=18$, số lớn $=48-18=30$.\n\n- **Tìm hai số khi biết hiệu và tỉ số:**\n    - Hiệu 36, tỉ số 8:5. Hiệu số phần $8-5=3$, số lớn $=36:3\\times8=96$, số bé $=96-36=60$.\n\n- **Bài toán tỉ lệ bản đồ:**\n    - Khoảng cách thật 30m = 3000cm, tỉ lệ 1:500, trên bản đồ $=3000:500=6$cm.\n    - Độ dài 41mm trên bản đồ tỉ lệ 1:2.000.000, thật $=41\\times2.000.000=82.000.000$mm $=82$km.\n    - 2cm bản đồ ứng với 200m thực: $200m=20.000cm$, tỉ lệ $=2:20.000=1:10.000$.\n\n- **Chuyển đổi số thập phân và phần trăm:**\n    - $0,235 \\rightarrow 23,5\\%$.\n    - $0,36 \\rightarrow 36\\%$.\n    - Tìm tỉ số phần trăm của 15 và 60: $15:60=0,25=25\\%$.\n    - Tìm tỉ số phần trăm của 23 và 60: $23:60\\approx 0,3833=38,33\\%$.\n    - Tìm 25% của 80: $80\\times\\frac{25}{100}=20$ hoặc $80:100\\times25=20$.\n\n**B. Hình học và đo lường**\n\n- **Diện tích tam giác:** Nếu đáy $a=6$, chiều cao $h=4$, $S=\\frac{6\\times4}{2}=12$.\n- **Diện tích hình thang:** Đáy $a=6$, $b=4$, $h=5$, $S=\\frac{(6+4)\\times5}{2}=25$.\n- **Chu vi hình tròn:** Đường kính $d=10$cm, $C=10\\times3,14=31,4$cm.\n- **Diện tích hình tròn:** Bán kính $r=5$cm, $S=5\\times5\\times3,14=78,5$cm².\n- **Diện tích xung quanh lập phương cạnh 6cm:** $6\\times6\\times4=144$cm².\n- **Diện tích toàn phần lập phương cạnh 5cm:** $5\\times5\\times6=150$cm².\n- **Thể tích lập phương cạnh 3cm:** $3\\times3\\times3=27$cm³.\n- **Diện tích xung quanh hình hộp chữ nhật (20m, 7m, 10m):** $(20+7)\\times2\\times10=540$cm².\n- **Diện tích toàn phần hình hộp chữ nhật (5,4cm, 2cm, 3cm):** $(5,4+2)\\times2\\times3=44,4$cm², cộng $2\\times5,4\\times2=21,6$cm², tổng $66$cm².\n- **Thể tích hình hộp chữ nhật (9cm, 5cm, 6cm):** $9\\times5\\times6=270$cm³.\n\n**C. Đo lường**\n\n- **Đổi đơn vị diện tích/ thể tích:** $1km^2=100hm^2$, $1m^3=1000dm^3$, $1dm^3=1000cm^3$.\n- **Đổi thời gian:** $1 năm=12 tháng=365(366) ngày$; $1 ngày=24 giờ$; $1 giờ=60 phút$; $1 phút=60 giây$.\n- **Phép tính với thời gian:**\n    - $2$ phút $40$ giây $+1$ phút $20$ giây $=4$ phút.\n    - $4$ giờ $10$ phút $-2$ giờ $30$ phút $=1$ giờ $40$ phút.\n    - $1$ giờ $25$ phút $\\times3=4$ giờ $15$ phút.\n    - $4$ phút $12$ giây $:4=1$ phút $3$ giây.\n\n- **Vận tốc, quãng đường, thời gian:**\n    - Vận tốc: Xe chạy $100$km trong $2$ giờ, $v=100:2=50$km/h.\n    - Quãng đường: Máy bay $860$km/h trong $3,5$ giờ, $s=860\\times3,5=3010$km.\n    - Thời gian: Xe đi $180$km, vận tốc $60$km/h, $t=180:60=3$ giờ.\n\n**D. Thống kê & Xác suất**\n\n- **Bảng thống kê chiều dài"
    },
    {
      "index": 2,
      "title": "NGỮ VĂN",
      "chapter_stem": "ch002_NGU_VAN",
      "summary": "**Tóm tắt chi tiết chương \"NGỮ VĂN\" (theo chuẩn CliffsNotes):**\n\n---\n\n### 1. Luận điểm trung tâm\n\nChương \"Ngữ văn\" tổng hợp các kiến thức nền tảng về tiếng Việt và kỹ năng làm văn dành cho học sinh, bao gồm nhận diện và vận dụng đúng các quy tắc ngữ pháp, sử dụng vốn từ vựng phong phú, các biện pháp tu từ, cũng như kỹ năng viết các dạng bài và đoạn văn thực tế. Tác giả hướng đến mục tiêu giúp người học nắm vững quy tắc chính tả, ngữ pháp, vận dụng linh hoạt các kiểu câu, từ loại, đồng thời phát triển khả năng cảm thụ văn học và thể hiện tư duy sáng tạo trong các bài viết.\n\n---\n\n### 2. Khái niệm & framework được giới thiệu\n\n- **Quy tắc viết hoa:** Cách viết hoa tên riêng (người, địa lý nước ngoài), trường hợp danh từ chung được viết hoa để thể hiện sự tôn trọng.\n- **Thành ngữ – tục ngữ:** Định nghĩa, công dụng và giải nghĩa các thành ngữ, tục ngữ thông dụng trong giao tiếp, văn học.\n- **Từ đồng nghĩa:** Phân biệt từ đồng nghĩa hoàn toàn và không hoàn toàn, cách vận dụng phù hợp ngữ cảnh.\n- **Từ đa nghĩa:** Định nghĩa, phân biệt nghĩa gốc và nghĩa chuyển, tác dụng làm giàu diễn đạt.\n- **Đại từ:** Phân loại (xưng hô, nghi vấn, thay thế), cách nhận diện và vận dụng trong câu.\n- **Kết từ:** Định nghĩa, các loại (nối, thời gian, nguyên nhân - kết quả, tương phản, điều kiện), cặp kết từ thông dụng.\n- **Câu đơn và câu ghép:** Định nghĩa, cấu trúc, cách nối các vế trong câu ghép (bằng từ nối hoặc không dùng từ nối).\n- **Dấu gạch ngang:** Công dụng (đánh dấu lời thoại, liệt kê, chú thích, giải thích, nối liên danh).\n- **Điệp từ, điệp ngữ:** Định nghĩa, tác dụng nhấn mạnh, tạo nhịp điệu, khẳng định ý.\n- **Liên kết câu trong đoạn văn:** Biện pháp lặp từ, thay thế từ, dùng từ nối để tạo mạch lạc, liên kết ý.\n- **Các kiểu đoạn văn và bài văn:** Hướng dẫn chi tiết về cấu trúc, cách viết các dạng bài: kể chuyện sáng tạo, miêu tả phong cảnh, tả người, đoạn văn cảm xúc, nêu ý kiến, giới thiệu nhân vật, báo cáo, chương trình hoạt động.\n\n---\n\n### 3. Ví dụ & câu chuyện thực tế\n\n**Bài 1: Quy tắc viết hoa**\n- Tên người, địa danh nước ngoài: Viết hoa chữ cái đầu mỗi bộ phận, dùng dấu gạch nối nếu nhiều tiếng (Ví dụ: Jean-Jacques Rousseau).\n- Danh từ chung viết hoa tôn trọng: “Bác Hồ”, “Vua Hùng”, “Ngày Quốc khánh”, “Đất Nước” – thể hiện sự kính trọng hoặc đánh dấu sự kiện lớn.\n\n**Bài 2: Thành ngữ – tục ngữ**\n- Thành ngữ: \"Chân cứng đá mềm\" (ý chí bền bỉ), \"Tôn sư trọng đạo\" (trọng thầy, trọng đạo nghĩa).\n- Tục ngữ: \"Ăn quả nhớ kẻ trồng cây\" (biết ơn), \"Đói cho sạch, rách cho thơm\" (giữ phẩm giá).\n- Giải nghĩa: \"Dám nghĩ dám làm\" (quyết đoán, dám hành động), \"Lá lành đùm lá rách\" (giúp đỡ người khó khăn), \"Uống nước nhớ nguồn\" (nhớ ơn nguồn cội).\n\n**Bài 3: Từ đồng nghĩa**\n- Hoàn toàn: “Bố”, “Cha”, “Ba” – thay thế cho nhau mà nghĩa không đổi.\n- Không hoàn toàn: “Nhanh” (tốc độ), “Vội” (gấp gáp), “Gấp” (khẩn trương, thường có tính cấp bách).\n\n**Bài 4: Từ đa nghĩa**\n- Từ “chân”: Nghĩa gốc là bộ phận cơ thể, nghĩa chuyển là phần tiếp xúc đất (“chân ghế”).\n- Từ “lưng”: Nghĩa gốc (phía sau thân người), nghĩa chuyển (“lưng trời” – vị trí giữa bầu trời và mặt đất).\n\n**Bài 5: Đại từ**\n- Đại từ xưng hô: tôi, ta, chúng tôi (ngôi thứ nhất); cậu, bạn, các bạn (ngôi thứ hai); họ, nó, chúng nó (ngôi thứ ba).\n- Đại từ nghi vấn: ai, gì, nào, sao, đâu, bao nhiêu.\n- Đại từ thay thế: thế, vậy, đó, này.\n- Danh từ làm đại từ xưng hô tùy vào ngữ cảnh: “bác” vừa là danh từ chỉ người thân, vừa làm đại từ xưng hô.\n\n**Bài 6: Kết từ**\n- Kết từ nối: và, với, hoặc, hay.\n- Kết từ chỉ thời gian: khi, lúc, trước khi, sau khi.\n- Kết từ nguyên nhân – kết quả: vì… nên…, do… nên….\n- Kết từ tương phản: nhưng, tuy nhiên.\n- Cặp kết từ: nếu… thì…, tuy… nhưng…, không những… mà còn…\n- Ví dụ: “Vì thức khuya nên tôi đi học muộn”; “Nếu bạn học chăm chỉ thì bạn sẽ thi đỗ”.\n\n**Câu đơn và câu ghép**\n- Câu đơn: một chủ ngữ – vị ngữ (“Cả lớp được cô khen.”)\n- Câu ghép: nhiều chủ ngữ – vị ngữ, có thể nối bằng kết từ/cặp từ hoặc không (“Hoa vừa học bài, vừa uống nước.”)\n\n**Bài 8: Dấu gạch ngang**\n- Đánh dấu lời thoại:  \n  – Em đi học chưa?  \n  – Em đi rồi.\n- Đánh dấu liệt kê:  \n  – Toán  \n  – Ngữ văn  \n  – Tiếng Anh\n- Đánh dấu chú thích: “Anh ấy — người bạn thân nhất của tôi — đã giúp đỡ tôi rất nhiều.”\n\n**Bài 9: Điệp từ, điệp ngữ**\n- Ví dụ:  \n  “Có vị phù sa  \n  Có hương sen thơm…”  \n  (từ “có” lặp lại nhiều lần để nhấn mạnh)\n- Tác dụng: làm nổi bật ý, tạo nhịp điệu.\n\n**Bài 10: Liên kết câu trong đoạn văn**\n- Lặp từ: \"Choất\" lặp lại để nhấn mạnh đối tượng miêu tả.\n- Thay thế từ: “chiếc váy này rất đẹp. Nó vừa được tôi mua tuần trước.”\n- Dùng từ nối: “Đầu tiên… Tiếp theo… Sau đó… Cuối cùng…”\n\n**Các dạng bài và đoạn văn thực tế:**\n- Bài văn kể chuyện sáng tạo: dựa trên truyện có sẵn, thêm chi tiết, đổi góc nhìn, hoặc sáng tạo kết thúc mới.\n- Bài văn tả phong cảnh: tả theo không gian, thời gian; kết hợp cảm xúc cá nhân.\n- Bài văn tả người: miêu tả ngoại hình, hoạt động, tính cách; mở bài trực tiếp/gián tiếp; kết bài mở rộng hoặc không.\n- Đoạn văn thể hiện cảm xúc: cấu trúc ba phần (giới thiệu, triển khai, kết); áp dụng cho sự việc, bài thơ, câu chuyện.\n- Đoạn văn nêu ý kiến xã hội: nêu ý kiến, lý do, dẫn chứng, khẳng định thái độ (tán thành/phản đối).\n- Đoạn văn giới thiệu nhân vật: nêu tên, đặc điểm, dẫn chứng, đánh giá nhân vật.\n- Báo cáo công việc: cấu trúc gồm quốc hiệu, tiêu ngữ, nội dung công việc, kết quả, ý kiến đề xuất.\n- Chương trình hoạt động: mục đích, thời gian, địa điểm, thành phần, các hoạt động, phân công nhiệm vụ.\n\n---\n\n### 4. Hướng dẫn & bước thực hiện\n\n- **Viết hoa:**  \n  1. Xác định tên riêng (người, địa lí nước ngoài), viết hoa chữ cái đầu mỗi bộ phận, dùng gạch nối nếu nhiều tiếng.  \n  2. Viết hoa danh từ chung nếu bày tỏ sự kính trọng đặc biệt (tên vĩ nhân, sự kiện lớn).\n- **Sử dụng thành ngữ – tục ngữ:**  \n  1. Xác định ngữ cảnh giao tiếp hoặc sáng tác văn học.  \n  2. Chọn thành ngữ, tục ngữ phù hợp ý nghĩa muốn diễn đạt.\n- **Phân biệt và sử dụng từ đồng nghĩa:**  \n  1. Xác định từ đồng nghĩa hoàn toàn hoặc không hoàn toàn.  \n  2. Chọn từ phù hợp ngữ cảnh, sắc thái.\n- **Nhận diện và vận dụng từ đa nghĩa:**  \n  1. Phân tích nghĩa gốc và nghĩa chuyển qua ngữ cảnh cụ thể.  \n  2. Sử dụng từ đa nghĩa hợp lý để tránh lặp từ, làm phong phú câu văn.\n- **Sử dụng đại từ:**  \n  1. Xác định chức năng đại từ (xưng hô, nghi vấn, thay thế).  \n  2. Chọn đại từ phù hợp ngữ cảnh để tránh mơ hồ hoặc thiếu lịch sự.\n- **Dùng kết từ trong câu ghép:**  \n  1. Liệt kê ý định diễn đạt.  \n  2. Chọn kết từ/cặp kết từ phù hợp (nguyên nhân – kết quả, điều kiện, tương phản…).\n  3. Có thể nối các vế câu không qua kết từ, dùng dấu phẩy, chấm phẩy, hai chấm.\n- **Viết đoạn/bài văn:**  \n  1. Lập dàn ý (mở bài, thân bài, kết bài).  \n  2. Miêu tả, kể chuyện, bày tỏ cảm xúc theo đúng cấu trúc từng dạng bài.  \n  3. Kiểm tra, hiệu chỉnh sau khi viết.\n- **Viết báo cáo, chương trình hoạt động:**  \n  1. Ghi quốc hiệu, tiêu ngữ hoặc tên tổ chức, địa điểm, thời gian.  \n  2. Trình bày nội dung, kết quả, đề xuất.  \n  3. Ký tên, ghi chức vụ.\n\n---\n\n### 5. Điểm then chốt cần nhớ\n\n1. **Nắm vững các quy tắc chính tả, ngữ pháp (đặc biệt là viết hoa, dùng từ, cấu trúc câu).**\n2. **Sử dụng linh hoạt thành ngữ, tục ngữ, từ đồng nghĩa, từ đa nghĩa, đại từ để làm giàu diễn đạt.**\n3. **Thành thạo các biện pháp tu từ (điệp từ, lặp từ, liên kết câu) để tăng tính mạch lạc, nhấn mạnh ý.**\n4. **Viết đúng cấu trúc các kiểu"
    },
    {
      "index": 3,
      "title": "TIẾNG ANH",
      "chapter_stem": "ch003_TIENG_ANH",
      "summary": "**TÓM TẮT CHƯƠNG “TIẾNG ANH”**\n\n---\n\n**1. Luận điểm trung tâm**\n\nChương “Tiếng Anh” cung cấp kiến thức nền tảng và hệ thống cho người học mới bắt đầu, tập trung vào các chủ điểm thiết yếu của ngữ pháp, từ vựng, cấu trúc câu, cách sử dụng động từ, thì, danh từ, mạo từ, giới từ, số thứ tự, đại từ sở hữu, từ chỉ lượng, động từ khuyết thiếu, cũng như các dạng câu hỏi thông dụng trong giao tiếp tiếng Anh. Mục tiêu của chương là giúp người học nắm vững các khái niệm cơ bản và sử dụng được tiếng Anh trong tình huống giao tiếp hàng ngày, xây dựng nền tảng vững chắc để học lên các trình độ cao hơn.\n\n---\n\n**2. Khái niệm & framework được giới thiệu**\n\n- **Động từ “to be”**: am/is/are – dùng để mô tả trạng thái, giới thiệu, vị trí, cảm xúc.\n- **Thì hiện tại đơn (Present Simple)**: Diễn tả thói quen, sự thật, lịch trình lặp lại.\n- **Thì hiện tại tiếp diễn (Present Continuous)**: Diễn tả hành động đang xảy ra tại thời điểm nói.\n- **Thì quá khứ đơn (Past Simple)**: Diễn tả hành động đã xảy ra và kết thúc trong quá khứ.\n- **Thì tương lai (Will/Be going to)**: Diễn tả hành động sẽ xảy ra, dự định hoặc dự đoán tương lai.\n- **Mạo từ a/an**: Dùng trước danh từ đếm được số ít, chọn a hay an theo âm đầu của từ.\n- **Danh từ đếm được/không đếm được**: Cách nhận biết, sử dụng với từ chỉ lượng phù hợp.\n- **Container words**: a bottle of, a cup of,... – đơn vị tách nhỏ danh từ không đếm được.\n- **There is/There are**: Cấu trúc diễn tả sự tồn tại, hiện diện.\n- **Từ chỉ lượng (some, many, much, a few, a little, a lot of)**: Phân biệt cách dùng với danh từ đếm được/không đếm được.\n- **Đại từ sở hữu (mine, yours, his, hers, ours, theirs)** và tính từ sở hữu (my, your, his, her, our, their).\n- **Sở hữu cách (‘s và ’)**: Cách chỉ quyền sở hữu.\n- **Giới từ chỉ vị trí**: in, on, under, behind, between, next to, in front of,...\n- **Số thứ tự (ordinal numbers)**: first, second, third, fourth,...\n- **Động từ khuyết thiếu (modal verbs)**: can, could, should, must, may,...\n- **Trạng từ tần suất (adverbs of frequency)**: always, usually, often, sometimes, rarely, never.\n- **Từ để hỏi (question words)**: what, who, where, when, why, how, which, how many, how much, how old.\n\n---\n\n**3. Ví dụ & câu chuyện thực tế**\n\n- **Động từ “to be”**:  \n  - I am a student. (Tôi là học sinh.)  \n  - She is happy. (Cô ấy vui.)  \n  - They are in the garden. (Họ ở trong vườn.)  \n  - Are you a student? (Bạn có phải là học sinh không?)\n- **A/An**:  \n  - a dog, a cat, a pen (danh từ bắt đầu bằng phụ âm);  \n  - an apple, an egg, an umbrella (danh từ bắt đầu bằng nguyên âm).  \n  - Đặc biệt: an hour (phát âm bắt đầu bằng nguyên âm), a university (phát âm bắt đầu bằng phụ âm “ju:”).\n- **Danh từ đếm được/không đếm được**:  \n  - Countable: a book, two books, a pencil, three pencils.  \n  - Uncountable: water, milk, sugar, rice (không dùng a/an, chỉ some/much/little).\n- **Container words**:  \n  - a bottle of water, a glass of milk, a cup of tea, a bowl of rice, a slice of cake, a piece of bread, a can of coke.\n- **There is/There are**:  \n  - There is a cat on the chair.  \n  - There are three dogs outside.  \n  - There isn’t any milk in the fridge.  \n  - Are there any apples in the basket?\n- **Từ chỉ lượng**:  \n  - I have some apples. (Tôi có vài quả táo.)  \n  - She has a lot of books. (Cô ấy có nhiều sách.)  \n  - I don’t have much time. (Tôi không có nhiều thời gian.)  \n  - There aren’t many chairs in the room.  \n  - I have a few pencils in my bag.  \n  - There is a little milk in the cup.\n- **Đại từ sở hữu**:  \n  - This is my book.  \n  - That bag is hers.  \n  - These toys are ours.\n- **Sở hữu cách**:  \n  - Nam’s book.  \n  - The students’ bags.\n- **Giới từ vị trí**:  \n  - The ball is in the box.  \n  - The book is on the table.  \n  - The cat is under the chair.  \n  - She is sitting next to her friend.\n- **Số thứ tự**:  \n  - She is the first in line.  \n  - My class is on the second floor.  \n  - Today is the third of June.\n- **Động từ khuyết thiếu**:  \n  - I can ride a bike.  \n  - May I go out?  \n  - Could I borrow your pen?  \n  - You should eat vegetables.  \n  - Students must wear uniforms.\n- **Thì hiện tại đơn**:  \n  - I go to school at 7 am.  \n  - She drinks milk every day.  \n  - They don’t like fish.  \n  - Does she like music?\n- **Trạng từ tần suất**:  \n  - She always gets up early.  \n  - I usually walk to school.  \n  - He never drinks coffee.\n- **Từ để hỏi**:  \n  - What is your name?  \n  - Where do you live?  \n  - How old are you?  \n  - How many pens do you have?\n- **Thì hiện tại tiếp diễn**:  \n  - She is reading a book now.  \n  - They are not playing football.  \n  - Are you watching TV?\n- **Thì quá khứ đơn**:  \n  - I was at the zoo yesterday.  \n  - He watched TV last night.  \n  - Did you watch TV last night?\n- **Thì tương lai**:  \n  - I will go to school tomorrow.  \n  - We are going to play football.  \n  - Are you going to watch TV?\n\n---\n\n**4. Hướng dẫn & bước thực hiện**\n\n- **Chia động từ “to be”**:  \n  1. Xác định chủ ngữ (I → am, He/She/It → is, You/We/They → are).\n  2. Đặt sau chủ ngữ để tạo câu khẳng định; thêm “not” để phủ định; đảo lên đầu để hỏi.\n- **Dùng a/an**:  \n  1. Xác định danh từ đếm được, số ít.  \n  2. Xem âm đầu tiên: nguyên âm → an, phụ âm → a.\n- **Phân biệt danh từ đếm được/không đếm được**:  \n  1. Nếu đếm được bằng số 1,2,3… → countable (dùng a/an/some/many/few).  \n  2. Không đếm được từng cái → uncountable (dùng some/much/little, không dùng a/an).\n- **Cấu trúc there is/there are**:  \n  1. Số ít/không đếm được → there is; số nhiều → there are.  \n  2. Phủ định thêm “not”; nghi vấn đảo “is/are” lên đầu.\n- **Sử dụng từ chỉ lượng**:  \n  1. Đếm được số nhiều → many, a few, some, a lot of.  \n  2. Không đếm được → much, a little, some, a lot of.\n- **Container words**:  \n  1. A/An + container word + of + danh từ không đếm được.\n- **Đại từ sở hữu & tính từ sở hữu**:  \n  1. My/your/his/her/our/their + danh từ.  \n  2. Mine/yours/his/hers/ours/theirs thay thế cho cụm danh từ đã nói trước.\n- **Sở hữu cách**:  \n  1. Danh từ số ít + ‘s + danh từ bị sở hữu.  \n  2. Danh từ số nhiều kết thúc bằng “s” chỉ thêm dấu ‘.\n- **Giới từ vị trí**:  \n  1. S + be + giới từ + nơi chốn/vật thể.\n- **Số thứ tự**:  \n  1. 1–3: first, second, third.  \n  2. Từ 4 trở đi: thêm -th vào số đếm (fourth, fifth…); lưu ý các số đặc biệt như fifth, eighth, ninth, twelfth.\n- **Động từ khuyết thiếu**:  \n  1. Modal verb + động từ nguyên thể (không “to”).\n- **Thì hiện tại đơn**:  \n  1. I/you/we/they → V nguyên mẫu; He/she/it → thêm -s/-es.  \n  2. Câu phủ định: do/does not + V nguyên mẫu.  \n  3. Câu hỏi: Do/Does + S + V nguyên mẫu?\n- **Trạng từ tần suất**:  \n  1. Động từ thường: trạng từ đứng trước.  \n  2. To be: trạng từ đứng sau.\n- **Từ để hỏi**:  \n  1. Question word + trợ động từ + chủ ngữ + động từ chính + ...?  \n  2. Với “to be”, không cần trợ động từ.\n- **Thì hiện tại tiếp diễn**:  \n  1. S + am/is/are + V-ing.  \n  2. Dấu hiệu: now, at the moment, look!\n- **Thì quá khứ đơn**:  \n  1. Was/were cho “to be”; V-ed cho động từ quy tắc; bảng động từ bất quy tắc phải học thuộc.  \n  2. Phủ định: did not + V nguyên mẫu; nghi vấn: Did + S + V nguyên mẫu?\n- **Thì tương lai**:  \n  1. Quyết định tại thời điểm nói hoặc dự đoán → will + V nguyên mẫu.  \n  2. Dự định có sẵn/dấu hiệu rõ ràng → am/is/are + going to + V nguyên mẫu.\n\n---\n\n**5. Điểm then chốt cần nhớ**\n\n1. **Nắm vững cách chia và sử dụng động từ “to be” với từng chủ ngữ trong các"
    }
  ],
  "full_summary": "Dưới đây là bản tóm tắt toàn bộ cuốn sách theo đúng cấu trúc yêu cầu, dựa trên tóm tắt từng chương đã cung cấp. Văn bản được trình bày mạch lạc, đầy đủ, dài tương đương 5-6 trang A4, nhằm giúp người đọc hiểu sâu toàn bộ nội dung mà không cần đọc bản gốc.\n\n---\n\n## Giới thiệu cuốn sách\n\n**Chủ đề trọng tâm**\n\nCuốn sách là tài liệu tổng hợp kiến thức cơ bản và nâng cao ở ba môn học nền tảng: Toán, Ngữ văn và Tiếng Anh, dành cho học sinh tiểu học và trung học cơ sở. Nội dung trải dài từ lý thuyết đến thực hành, từ các khái niệm nền tảng tới kỹ năng giải quyết vấn đề thực tế, giúp người học đạt được sự phát triển toàn diện cả về tư duy logic, ngôn ngữ và hội nhập quốc tế.\n\n**Luận điểm xuyên suốt**\n\nLuận điểm xuyên suốt của sách là: “Kiến thức vững chắc – Kỹ năng thực tiễn – Phát triển tư duy sáng tạo”. Tác giả không chỉ cung cấp các công thức, định nghĩa hay mẹo làm bài, mà còn tập trung rèn luyện tư duy phân tích, kỹ năng vận dụng và khả năng sáng tạo của học sinh qua các ví dụ thực tế, bài tập đa dạng, tình huống gần gũi.\n\n**Đối tượng độc giả lý tưởng**\n\n- Học sinh tiểu học, trung học cơ sở đang củng cố hoặc mở rộng kiến thức ba môn học trọng điểm.\n- Giáo viên, phụ huynh muốn có tài liệu hệ thống, dễ tra cứu để hỗ trợ việc dạy và học.\n- Những người lớn muốn ôn tập, tự kiểm tra lại kiến thức nền tảng, đặc biệt là khi hướng dẫn con em học tập.\n\n**Lý do nên đọc**\n\n- Sách tổng hợp đầy đủ, súc tích, dễ hiểu, kèm ví dụ cụ thể.\n- Mỗi chương đều có hướng dẫn từng bước, giúp người học tự tin áp dụng.\n- Đề cao tính thực tiễn: lấy ví dụ từ đời sống, bài toán thực tế, tình huống giao tiếp thường gặp.\n- Sách giúp người đọc không chỉ làm được bài mà còn hiểu bản chất kiến thức, phát triển tư duy giải quyết vấn đề.\n- Là tài liệu gối đầu giường để ôn tập, hệ thống hóa kiến thức hoặc tra cứu nhanh khi cần thiết.\n\n---\n\n## Nội dung từng chương\n\n### Chương 1: Toán\n\n#### Ý tưởng & luận điểm chính\n\nChương Toán xây dựng cho học sinh một hệ thống kiến thức nền tảng về số học, đại lượng, hình học, các phép đo lường, thống kê và xác suất. Tác giả đặc biệt chú trọng vào khả năng nhận diện, hiểu và vận dụng các loại số, phép toán, các dạng hình học và công thức đo lường, cũng như bước đầu làm quen với tư duy xác suất – thống kê. Các ví dụ thực tiễn giúp người học liên hệ và giải quyết bài toán đời sống, từ tính toán chi tiêu, đo lường thực phẩm, đến đọc hiểu biểu đồ, dự đoán xác suất sự kiện.\n\n#### Ví dụ, câu chuyện, case study tiêu biểu\n\n##### Số học\n\n- **Chuyển đổi phân số và phân số thập phân:** Khi chia bánh pizza cho 10 người, mỗi người được 1/10 cái bánh – đây là phân số thập phân. Nếu chia cho 4 người, mỗi người 1/4, nhưng muốn so sánh với 1/10, phải quy đổi: 1/4 = 2,5/10 = 25/100.\n- **Tính tỉ số phần trăm:** Khi giảm giá 15% trên hóa đơn 200, học sinh thực hành: 200 x 15/100 = 30, số tiền phải trả là 170.\n- **Bài toán tỉ lệ bản đồ:** Nếu gia đình đi du lịch, muốn xác định khoảng cách thật dựa trên bản đồ, học sinh biết cách quy đổi tỉ lệ và đơn vị đo.\n\n##### Hình học – Đo lường\n\n- **Diện tích thực tế:** Khi cần trải thảm phòng khách hình chữ nhật (dài 4m, rộng 3m), học sinh biết tính diện tích: 4 x 3 = 12m².\n- **Thể tích hộp quà:** Đóng gói quà trong hộp hình lập phương cạnh 10cm, thể tích = 10³ = 1000cm³.\n- **Tính toán thời gian:** Nếu muốn nấu chín món ăn trong 1h 15 phút, học sinh biết đổi ra 75 phút để đặt hẹn giờ chính xác.\n\n##### Thống kê – Xác suất\n\n- **Biểu đồ:** Khi thống kê điểm kiểm tra của lớp, học sinh tự lập bảng, vẽ biểu đồ cột so sánh số bạn đạt từng mức điểm.\n- **Xác suất thực nghiệm:** Tung một đồng xu 10 lần, đếm số lần xuất hiện mặt “Ngửa”, tính xác suất thực tế.\n\n#### Điểm then chốt cần nhớ\n\n- Hiểu bản chất các loại số (phân số, thập phân, hỗn số) và phép toán với chúng.\n- Nhớ công thức diện tích, chu vi, thể tích các hình cơ bản, biết vận dụng vào tình huống thực tế.\n- Nắm quy tắc đổi đơn vị đo lường, tính vận tốc, quãng đường, thời gian.\n- Biết cách đọc, lập bảng, vẽ biểu đồ, tính xác suất thực nghiệm đơn giản.\n\n---\n\n### Chương 2: Ngữ văn\n\n#### Ý tưởng & luận điểm chính\n\nChương Ngữ văn hệ thống hóa toàn bộ kiến thức tiếng Việt – từ quy tắc chính tả, từ loại, ngữ pháp, các biện pháp tu từ đến kỹ năng làm bài văn theo từng kiểu. Đặc biệt, chương nhấn mạnh việc phát triển năng lực cảm thụ, sáng tạo và tư duy phản biện của học sinh thông qua bài tập thực tế, phân tích tác phẩm, luyện viết các dạng đoạn văn, bài văn phù hợp nhiều tình huống học tập và đời sống.\n\n#### Ví dụ, câu chuyện, case study tiêu biểu\n\n##### Chính tả – Ngữ pháp\n\n- **Quy tắc viết hoa:** Khi viết tên “Nguyễn Du”, học sinh biết phải viết hoa từng bộ phận, hiểu lý do phải viết hoa “Đất Nước” khi thể hiện sự tôn kính trong thơ.\n- **Từ đồng nghĩa:** Khi viết văn, học sinh dùng “bố”, “cha”, “ba” luân phiên để tránh lặp từ nhàm chán.\n- **Từ đa nghĩa:** Phân tích từ “mắt” trong “đôi mắt em” (nghĩa gốc) với “mắt của kim khâu” (nghĩa chuyển).\n\n##### Biện pháp tu từ\n\n- **Điệp từ:** Trong thơ “Bác ơi”, tác giả lặp lại từ “Bác” để nhấn mạnh tình cảm sâu sắc.\n- **Liên kết câu:** Khi viết đoạn văn kể chuyện, học sinh lặp lại từ “cô giáo” hoặc dùng đại từ “cô” để tạo liên kết, tránh rối ý.\n\n##### Các dạng bài thực tế\n\n- **Kể chuyện sáng tạo:** Yêu cầu học sinh viết lại truyện Tấm Cám dưới góc nhìn của Cám, giúp các em rèn kỹ năng sáng tạo và đồng cảm.\n- **Báo cáo công việc, chương trình hoạt động:** Khi tổ chức hội thi ở lớp, học sinh tự viết báo cáo tổng kết, lập chương trình phân công nhiệm vụ.\n\n#### Điểm then chốt cần nhớ\n\n- Thuộc quy tắc viết hoa, dùng từ, cấu trúc câu đơn/câu ghép.\n- Sử dụng linh hoạt thành ngữ, tục ngữ, từ đồng nghĩa – đa nghĩa, đại từ.\n- Biết vận dụng các biện pháp tu từ để tăng sức biểu đạt, nhấn mạnh ý.\n- Thành thạo viết các kiểu đoạn văn, bài văn, báo cáo, chương trình hoạt động.\n- Phát triển khả năng cảm thụ, trình bày ý kiến cá nhân, liên hệ đời sống.\n\n---\n\n### Chương 3: Tiếng Anh\n\n#### Ý tưởng & luận điểm chính\n\nChương Tiếng Anh cung cấp nền tảng vững chắc cho người học mới bắt đầu, giúp hình thành tư duy tiếng Anh logic và hệ thống qua các chủ điểm ngữ pháp, từ vựng, cấu trúc câu và kỹ năng giao tiếp thiết yếu. Nội dung đi từ cơ bản (động từ to be, danh từ, mạo từ, giới từ) đến các thì, động từ khuyết thiếu, trạng từ tần suất và đa dạng dạng câu hỏi – trả lời, hướng đến mục tiêu giúp người học tự tin ứng dụng tiếng Anh trong đời sống hàng ngày và làm nền tảng học nâng cao.\n\n#### Ví dụ, câu chuyện, case study tiêu biểu\n\n##### Ngữ pháp cơ bản\n\n- **Động từ to be:** “I am a student”, “She is happy”, “They are in the garden” – các câu giới thiệu bản thân, mô tả trạng thái.\n- **A/An:** “a cat”, “an apple”, phân biệt theo âm đầu từ, không phải chỉ dựa vào chữ cái.\n- **There is/are:** “There is a book on the table”, “Are there any students in the class?”\n\n##### Danh từ, từ chỉ lượng, container words\n\n- **Countable/Uncountable:** “a pen”, “two apples” vs. “some water”, “much rice”.\n- **Container words:** “a bottle of milk”, “a slice of bread” – biết chia nhỏ các danh từ không đếm được, áp dụng khi đi siêu thị, gọi món ăn.\n\n##### Đại từ sở hữu, sở hữu cách\n\n- **My/your/his/her...:** “This is my book”, “That is hers”.\n- **Sở hữu cách:** “Nam’s bag”, “the students’ room”.\n\n##### Giới từ, số thứ tự, động từ khuyết thiếu\n\n- **Giới từ vị trí:** “The ball is under the table”, “She is sitting next to her friend”.\n- **Số thứ tự:** “first”, “second”, “third”, áp dụng khi giới thiệu thứ tự, ngày tháng, lớp học.\n- **Modal verbs:** “I can swim”, “You should do homework”, “May I go out?”\n\n##### Các thì – cấu trúc câu hỏi\n\n- **Present Simple:** “I go to school at 7 am”, “Does she like music?”\n- **Present Continuous:** “She is reading a book now”, “Are you watching TV?”\n- **Past Simple:** “He watched TV last night”, “Did you go to school yesterday?”\n- **Future:** “I will go to school tomorrow”, “We are going to play football.”\n\n##### Dạng câu hỏi – trạng từ tần suất\n\n- **Question words:** “What is your name?”, “Where do you live?”, “How many pens do you have?”\n- **Adverbs of frequency:** “always”, “usually”, “often”, “never”, giúp mô tả thói quen.\n\n#### Điểm then chốt cần nhớ\n\n- Nắm vững chia động từ “to be”, cách dùng danh từ đếm được/không đếm được, mạo từ a/an.\n- Sử dụng linh hoạt container words, từ chỉ lượng, đại từ sở hữu – sở hữu cách.\n- Biết cách đặt câu với giới từ vị trí, số thứ tự.\n- Thuần thục các thì cơ bản: hiện tại đơn, tiếp diễn, quá khứ đơn, tương lai.\n- Thành thạo đặt câu hỏi, trả lời, dùng trạng từ tần suất trong giao tiếp hàng ngày.\n\n---\n\n## Các khái niệm & framework cốt lõi\n\n### Toán\n\n1. **Phân số, số thập phân, hỗn số:**  \n   - Nhận diện, chuyển đổi, thực hiện phép tính.\n   - **Quy tắc làm tròn:** Xác định hàng cần làm tròn, xét chữ số liền sau.\n2. **Tỉ số, tỉ số phần trăm:**  \n   - Tính toán, so sánh, ứng dụng trong bài toán thực tế (giảm giá, chia phần, bản đồ).\n3. **Công thức diện tích, chu vi, thể tích:**  \n   - Tam giác, hình thang, hình tròn, lập phương, hộp chữ nhật.\n   - Đổi đơn vị đo diện tích, thể tích, thời gian.\n4. **Quan hệ vận tốc, quãng đường, thời gian:**  \n   - V = S/T; S = V x T; T = S/V.\n5. **Biểu diễn thống kê, xác suất thực nghiệm:**  \n   - Lập bảng, vẽ biểu đồ cột/hình quạt, tính xác suất qua tần suất thực tế.\n\n### Ngữ văn\n\n1. **Quy tắc chính tả, viết hoa:**  \n   - Tên riêng, danh từ tôn trọng, sự kiện lớn.\n2. **Từ loại:**  \n   - Phân biệt danh từ, động từ, tính từ, đại từ, kết từ.\n3. **Câu đơn, câu ghép:**  \n   - Cấu trúc, cách nối vế, dùng kết từ.\n4. **Biện pháp tu từ:**  \n   - Điệp từ, lặp từ, liên kết câu, sử dụng thành ngữ – tục ngữ.\n5. **Các kiểu đoạn/bài văn:**  \n   - Kể chuyện sáng tạo, miêu tả, cảm xúc, nghị luận, báo cáo, chương trình hoạt động.\n\n### Tiếng Anh\n\n1. **Động từ to be, mạo từ a/an:**  \n   - Chia đúng theo chủ ngữ, chọn mạo từ theo âm đầu.\n2. **Danh từ đếm được/không đếm được, container words:**  \n   - Cách dùng từ chỉ lượng, ghép container word + danh từ.\n3. **There is/There are:**  \n   - Cấu trúc xác định sự tồn tại, phân biệt số ít/nhiều.\n4. **Đại từ sở hữu, sở hữu cách:**  \n   - My/your/his/her... và mine/yours/hers..., cách dùng ‘s/’ cho quyền sở hữu.\n5. **Giới từ vị trí, số thứ tự:**  \n   - In, on, under, next to...; first, second, third...\n6. **Modal verbs:**  \n   - Can, could, should, must, may... + động từ nguyên thể.\n7. **Các thì cơ bản:**  \n   - Hiện tại đơn, tiếp diễn, quá khứ đơn, tương lai (will, be going to).\n8. **Trạng từ tần suất, từ để hỏi:**  \n   - Always, usually, often, sometimes...; what, who, where, how, how many...\n\n---\n\n## Bài học thực tiễn\n\n### Toán\n\n- **Giải quyết các tình huống chi tiêu, mua bán, giảm giá:**  \n  Khi đi siêu thị, học sinh dùng tỉ số phần trăm để tính giá sau giảm, tổng tiền cần trả.\n- **Tính toán diện tích, thể tích trong đời sống:**  \n  Khi bố mẹ sửa nhà, học sinh giúp tính diện tích tường cần sơn, thể tích bể nước.\n- **Đổi đơn vị đo lường:**  \n  Biết quy đổi giữa mét, centimet, lít, mililít, phục vụ việc nấu ăn, mua bán.\n- **Dự đoán xác suất sự kiện:**  \n  Khi chơi trò chơi, biết tính xác suất thắng/thua dựa trên số lần thử.\n\n### Ngữ văn\n\n- **Viết email, thư, báo cáo, chương trình hoạt động:**  \n  Ứng dụng khi cần gửi thông tin, tường thuật sự kiện, lên kế hoạch sinh hoạt lớp/nhóm.\n- **Trình bày ý kiến, cảm xúc bằng đoạn văn rõ ràng:**  \n  Khi phát biểu, tranh luận, viết nhật ký, báo tường, học sinh biết cách nêu ý chính, dẫn chứng, kết luận.\n- **Hiểu và vận dụng thành ngữ, tục ngữ:**  \n  Giao tiếp linh hoạt, thể hiện sắc thái, làm giàu vốn từ và diễn đạt.\n\n### Tiếng Anh\n\n- **Giao tiếp cơ bản:**  \n  Giới thiệu bản thân, hỏi đường, mua sắm (“How much is this?”, “Where is the toilet?”).\n- **Đặt câu hỏi, trả lời linh hoạt:**  \n  Biết hỏi tên, tuổi, số lượng, vị trí (“What is your name?”, “How old are you?”, “Where is the book?”).\n- **Sử dụng đúng thì, mạo từ, danh từ:**  \n  Tránh lỗi sai khi nói, viết, đặc biệt trong các kỳ kiểm tra, giao tiếp thực tế.\n- **Giao tiếp trong các tình huống hàng ngày:**  \n  Hỏi xin phép (“May I go out?”), đề nghị (“Could you help me?”), khuyên bảo (“You should listen to your parents.”).\n\n---\n\n## Kết luận\n\n**Giá trị cốt lõi**\n\nCuốn sách là cẩm nang tổng hợp ba môn học nền tảng nhất của giáo dục phổ thông: Toán, Ngữ văn, Tiếng Anh. Giá trị lớn nhất mà sách mang lại không chỉ là hệ thống kiến thức, công thức, định nghĩa, mà còn là kỹ năng thực hành, khả năng vận dụng, tư duy logic và sáng tạo. Sách giúp người học không bị “học vẹt”, mà thực sự hiểu – nhớ – áp dụng được vào đời sống.\n\n**Nên đọc nếu bạn đang gặp vấn đề gì?**\n\n- Khó khăn trong việc hệ thống hóa kiến thức ba môn học lớn, đặc biệt trước các kỳ kiểm tra, thi chuyển cấp.\n- Muốn củng cố lại nền tảng, tránh hổng kiến thức, học chắc – hiểu sâu, không nhầm lẫn giữa các khái niệm.\n- Gặp lúng túng khi giải quyết các tình huống thực tế (tính toán chi tiêu, viết báo cáo, giao tiếp tiếng Anh hàng ngày).\n- Cần một tài liệu tra cứu nhanh, rõ ràng, có ví dụ thực tế, dễ áp dụng cho cả học sinh, phụ huynh, giáo viên.\n\n**Tác động lớn nhất cuốn sách có thể tạo ra**\n\n- Giúp học sinh tự tin hơn trong học tập, chủ động giải quyết các bài toán, tình huống đời sống bằng kiến thức đã học.\n- Nâng cao khả năng tư duy phân tích, tổng hợp, sáng tạo và ứng dụng thực tiễn – những năng lực cốt lõi của thế kỷ 21.\n- Trang bị nền tảng ngôn ngữ vững chắc (cả tiếng Việt và tiếng Anh), tạo bước đệm cho hội nhập quốc tế, học tập suốt đời.\n- Là công cụ hỗ trợ đắc lực cho giáo viên, phụ huynh trong việc đồng hành, hướng dẫn, kiểm tra quá trình học của trẻ.\n\n---\n\n**Tóm lại**, cuốn sách không chỉ là “bảng tra cứu” kiến thức, mà còn là nguồn cảm hứng cho học sinh khám phá, vận dụng, phát triển bản thân qua ba môn học thiết yếu. Đọc sách này, bạn sẽ không còn sợ “hổng kiến thức”, mà sẽ cảm thấy môn Toán, Ngữ văn, Tiếng Anh trở nên gần gũi, hữu ích và thú vị hơn bao giờ hết."
}